<?xml version="1.0" encoding="UTF-8"?>
<Erhalter>
  <ErhKz>001</ErhKz>
  <MeldeDatum>15112014</MeldeDatum>
  <StudierendenBewerberMeldung>
    <Studiengang>
      <StgKz>269</StgKz>
		<StudentIn>
			<PersKz>1120269025</PersKz>
			<OrgFormCode>2</OrgFormCode>
			<GeburtsDatum>04011990</GeburtsDatum>
			<Geschlecht>W</Geschlecht>
			<SVNR>2945040190</SVNR>
			<StaatsangehoerigkeitCode>A</StaatsangehoerigkeitCode>
			<HeimatPLZ>8045</HeimatPLZ>
			<HeimatGemeinde>Graz</HeimatGemeinde>
			<HeimatStrasse><![CDATA[Rotmoosweg 32f]]></HeimatStrasse>
			<HeimatNation>A</HeimatNation>
				<ZugangCode>9</ZugangCode>
				<ZugangDatum>24062008</ZugangDatum>
			<ZugangMaStgCode>5</ZugangMaStgCode>
			<ZugangMaStgDatum>17022012</ZugangMaStgDatum>
				<Ausstellungsstaat>A</Ausstellungsstaat>
			<BeginnDatum>17022012</BeginnDatum>
			<BeendigungsDatum>01092014</BeendigungsDatum>
			<Ausbildungssemester>4</Ausbildungssemester>
			<StudStatusCode>3</StudStatusCode>
			<BerufstaetigkeitCode>0</BerufstaetigkeitCode>
					<StandortCode>14</StandortCode>
				<BMWFWfoerderrelevant>J</BMWFWfoerderrelevant>
		</StudentIn>
		<StudentIn>
			<PersKz>1210269001</PersKz>
			<OrgFormCode>2</OrgFormCode>
			<GeburtsDatum>03101988</GeburtsDatum>
			<Geschlecht>W</Geschlecht>
			<SVNR>3435031088</SVNR>
			<StaatsangehoerigkeitCode>A</StaatsangehoerigkeitCode>
			<HeimatPLZ>7423</HeimatPLZ>
			<HeimatGemeinde>Pinkafeld</HeimatGemeinde>
			<HeimatStrasse><![CDATA[Hauptstraße 34/3]]></HeimatStrasse>
			<HeimatNation>A</HeimatNation>
				<ZugangCode>14</ZugangCode>
				<ZugangDatum>20062007</ZugangDatum>
			<ZugangMaStgCode>1</ZugangMaStgCode>
			<ZugangMaStgDatum>13072012</ZugangMaStgDatum>
				<Ausstellungsstaat>A</Ausstellungsstaat>
			<BeginnDatum>01092012</BeginnDatum>
			<Ausbildungssemester>50</Ausbildungssemester>
			<StudStatusCode>1</StudStatusCode>
			<BerufstaetigkeitCode>10</BerufstaetigkeitCode>
					<StandortCode>14</StandortCode>
				<BMWFWfoerderrelevant>J</BMWFWfoerderrelevant>
		</StudentIn>
		<StudentIn>
			<PersKz>1210269002</PersKz>
			<OrgFormCode>2</OrgFormCode>
			<GeburtsDatum>15051987</GeburtsDatum>
			<Geschlecht>W</Geschlecht>
			<SVNR>1893150587</SVNR>
			<StaatsangehoerigkeitCode>A</StaatsangehoerigkeitCode>
			<HeimatPLZ>8970</HeimatPLZ>
			<HeimatGemeinde>Schladming</HeimatGemeinde>
			<HeimatStrasse><![CDATA[Langegasse 384/2]]></HeimatStrasse>
			<HeimatNation>A</HeimatNation>
				<ZugangCode>9</ZugangCode>
				<ZugangDatum>16072005</ZugangDatum>
			<ZugangMaStgCode>3</ZugangMaStgCode>
			<ZugangMaStgDatum>01102009</ZugangMaStgDatum>
				<Ausstellungsstaat>A</Ausstellungsstaat>
			<BeginnDatum>01092012</BeginnDatum>
			<BeendigungsDatum>01072014</BeendigungsDatum>
			<Ausbildungssemester>4</Ausbildungssemester>
			<StudStatusCode>3</StudStatusCode>
			<BerufstaetigkeitCode>7</BerufstaetigkeitCode>
					<StandortCode>14</StandortCode>
				<BMWFWfoerderrelevant>J</BMWFWfoerderrelevant>
		</StudentIn>
		<StudentIn>
			<PersKz>1210269003</PersKz>
			<OrgFormCode>2</OrgFormCode>
			<GeburtsDatum>08041989</GeburtsDatum>
			<Geschlecht>W</Geschlecht>
			<SVNR>3967080489</SVNR>
			<StaatsangehoerigkeitCode>A</StaatsangehoerigkeitCode>
			<HeimatPLZ>8230</HeimatPLZ>
			<HeimatGemeinde>Hartberg</HeimatGemeinde>
			<HeimatStrasse><![CDATA[Hauptplatz 1/7]]></HeimatStrasse>
			<HeimatNation>A</HeimatNation>
				<ZugangCode>14</ZugangCode>
				<ZugangDatum>05062008</ZugangDatum>
			<ZugangMaStgCode>1</ZugangMaStgCode>
			<ZugangMaStgDatum>13072012</ZugangMaStgDatum>
				<Ausstellungsstaat>A</Ausstellungsstaat>
			<BeginnDatum>01092012</BeginnDatum>
			<BeendigungsDatum>30062014</BeendigungsDatum>
			<Ausbildungssemester>4</Ausbildungssemester>
			<StudStatusCode>3</StudStatusCode>
			<BerufstaetigkeitCode>7</BerufstaetigkeitCode>
					<StandortCode>14</StandortCode>
				<BMWFWfoerderrelevant>J</BMWFWfoerderrelevant>
		</StudentIn>
		<StudentIn>
			<PersKz>1210269004</PersKz>
			<OrgFormCode>2</OrgFormCode>
			<GeburtsDatum>02031990</GeburtsDatum>
			<Geschlecht>W</Geschlecht>
			<SVNR>4392020390</SVNR>
			<StaatsangehoerigkeitCode>A</StaatsangehoerigkeitCode>
			<HeimatPLZ>8313</HeimatPLZ>
			<HeimatGemeinde>Breitenfeld an der Rittschein</HeimatGemeinde>
			<HeimatStrasse><![CDATA[Breitenfeld 122]]></HeimatStrasse>
			<HeimatNation>A</HeimatNation>
				<ZugangCode>14</ZugangCode>
				<ZugangDatum>10062009</ZugangDatum>
			<ZugangMaStgCode>1</ZugangMaStgCode>
			<ZugangMaStgDatum>13072012</ZugangMaStgDatum>
				<Ausstellungsstaat>A</Ausstellungsstaat>
			<BeginnDatum>01092012</BeginnDatum>
			<BeendigungsDatum>01072014</BeendigungsDatum>
			<Ausbildungssemester>4</Ausbildungssemester>
			<StudStatusCode>3</StudStatusCode>
			<BerufstaetigkeitCode>0</BerufstaetigkeitCode>
					<StandortCode>14</StandortCode>
				<BMWFWfoerderrelevant>J</BMWFWfoerderrelevant>
		</StudentIn>
		<StudentIn>
			<PersKz>1210269005</PersKz>
			<OrgFormCode>2</OrgFormCode>
			<GeburtsDatum>29061987</GeburtsDatum>
			<Geschlecht>W</Geschlecht>
			<SVNR>2509290687</SVNR>
			<StaatsangehoerigkeitCode>A</StaatsangehoerigkeitCode>
			<HeimatPLZ>7400</HeimatPLZ>
			<HeimatGemeinde>Oberwart</HeimatGemeinde>
			<HeimatStrasse><![CDATA[Röntgengasse 24/4]]></HeimatStrasse>
			<HeimatNation>A</HeimatNation>
				<ZugangCode>13</ZugangCode>
				<ZugangDatum>12062006</ZugangDatum>
			<ZugangMaStgCode>4</ZugangMaStgCode>
			<ZugangMaStgDatum>25012012</ZugangMaStgDatum>
				<Ausstellungsstaat>A</Ausstellungsstaat>
			<BeginnDatum>01092012</BeginnDatum>
			<BeendigungsDatum>01072014</BeendigungsDatum>
			<Ausbildungssemester>4</Ausbildungssemester>
			<StudStatusCode>3</StudStatusCode>
			<BerufstaetigkeitCode>9</BerufstaetigkeitCode>
					<StandortCode>14</StandortCode>
				<BMWFWfoerderrelevant>J</BMWFWfoerderrelevant>
		</StudentIn>
		<StudentIn>
			<PersKz>1210269006</PersKz>
			<OrgFormCode>2</OrgFormCode>
			<GeburtsDatum>10101990</GeburtsDatum>
			<Geschlecht>W</Geschlecht>
			<SVNR>1982101090</SVNR>
			<StaatsangehoerigkeitCode>A</StaatsangehoerigkeitCode>
			<HeimatPLZ>3542</HeimatPLZ>
			<HeimatGemeinde>Gföhl</HeimatGemeinde>
			<HeimatStrasse><![CDATA[Kremserstraße 49]]></HeimatStrasse>
			<HeimatNation>A</HeimatNation>
				<ZugangCode>10</ZugangCode>
				<ZugangDatum>17062009</ZugangDatum>
			<ZugangMaStgCode>1</ZugangMaStgCode>
			<ZugangMaStgDatum>13072012</ZugangMaStgDatum>
				<Ausstellungsstaat>A</Ausstellungsstaat>
			<BeginnDatum>01092012</BeginnDatum>
			<BeendigungsDatum>01092014</BeendigungsDatum>
			<Ausbildungssemester>4</Ausbildungssemester>
			<StudStatusCode>3</StudStatusCode>
			<BerufstaetigkeitCode>0</BerufstaetigkeitCode>
					<StandortCode>14</StandortCode>
				<BMWFWfoerderrelevant>J</BMWFWfoerderrelevant>
		</StudentIn>
		<StudentIn>
			<PersKz>1210269007</PersKz>
			<OrgFormCode>2</OrgFormCode>
			<GeburtsDatum>10021987</GeburtsDatum>
			<Geschlecht>W</Geschlecht>
			<SVNR>2026100287</SVNR>
			<StaatsangehoerigkeitCode>A</StaatsangehoerigkeitCode>
			<HeimatPLZ>2230</HeimatPLZ>
			<HeimatGemeinde>Gänserndorf</HeimatGemeinde>
			<HeimatStrasse><![CDATA[Robert-Stolz-Gasse 4]]></HeimatStrasse>
			<HeimatNation>A</HeimatNation>
				<ZugangCode>14</ZugangCode>
				<ZugangDatum>13062006</ZugangDatum>
			<ZugangMaStgCode>1</ZugangMaStgCode>
			<ZugangMaStgDatum>13072012</ZugangMaStgDatum>
				<Ausstellungsstaat>A</Ausstellungsstaat>
			<BeginnDatum>01092012</BeginnDatum>
			<BeendigungsDatum>01092014</BeendigungsDatum>
			<Ausbildungssemester>4</Ausbildungssemester>
			<StudStatusCode>3</StudStatusCode>
			<BerufstaetigkeitCode>10</BerufstaetigkeitCode>
					<StandortCode>14</StandortCode>
				<BMWFWfoerderrelevant>J</BMWFWfoerderrelevant>
		</StudentIn>
		<StudentIn>
			<PersKz>1210269008</PersKz>
			<OrgFormCode>2</OrgFormCode>
			<GeburtsDatum>01051990</GeburtsDatum>
			<Geschlecht>W</Geschlecht>
			<SVNR>2203010590</SVNR>
			<StaatsangehoerigkeitCode>A</StaatsangehoerigkeitCode>
			<HeimatPLZ>2222</HeimatPLZ>
			<HeimatGemeinde>Bad Pirawarth</HeimatGemeinde>
			<HeimatStrasse><![CDATA[Föhrenwaldstraße 6]]></HeimatStrasse>
			<HeimatNation>A</HeimatNation>
				<ZugangCode>9</ZugangCode>
				<ZugangDatum>07062008</ZugangDatum>
			<ZugangMaStgCode>1</ZugangMaStgCode>
			<ZugangMaStgDatum>13072012</ZugangMaStgDatum>
				<Ausstellungsstaat>A</Ausstellungsstaat>
			<BeginnDatum>01092012</BeginnDatum>
			<BeendigungsDatum>30062014</BeendigungsDatum>
			<Ausbildungssemester>4</Ausbildungssemester>
			<StudStatusCode>3</StudStatusCode>
			<BerufstaetigkeitCode>10</BerufstaetigkeitCode>
					<StandortCode>14</StandortCode>
				<BMWFWfoerderrelevant>J</BMWFWfoerderrelevant>
		</StudentIn>
		<StudentIn>
			<PersKz>1210269009</PersKz>
			<OrgFormCode>2</OrgFormCode>
			<GeburtsDatum>13071989</GeburtsDatum>
			<Geschlecht>W</Geschlecht>
			<SVNR>3282130789</SVNR>
			<StaatsangehoerigkeitCode>A</StaatsangehoerigkeitCode>
			<HeimatPLZ>7501</HeimatPLZ>
			<HeimatGemeinde>Eisenzicken</HeimatGemeinde>
			<HeimatStrasse><![CDATA[Eisenzicken 90]]></HeimatStrasse>
			<HeimatNation>A</HeimatNation>
				<ZugangCode>9</ZugangCode>
				<ZugangDatum>26062007</ZugangDatum>
			<ZugangMaStgCode>6</ZugangMaStgCode>
			<ZugangMaStgDatum>13012012</ZugangMaStgDatum>
				<Ausstellungsstaat>A</Ausstellungsstaat>
			<BeginnDatum>01092012</BeginnDatum>
			<Ausbildungssemester>50</Ausbildungssemester>
			<StudStatusCode>1</StudStatusCode>
			<BerufstaetigkeitCode>7</BerufstaetigkeitCode>
					<StandortCode>14</StandortCode>
				<BMWFWfoerderrelevant>J</BMWFWfoerderrelevant>
		</StudentIn>
		<StudentIn>
			<PersKz>1210269010</PersKz>
			<OrgFormCode>2</OrgFormCode>
			<GeburtsDatum>03081990</GeburtsDatum>
			<Geschlecht>W</Geschlecht>
			<SVNR>2238030890</SVNR>
			<StaatsangehoerigkeitCode>A</StaatsangehoerigkeitCode>
			<HeimatPLZ>7400</HeimatPLZ>
			<HeimatGemeinde>Oberwart</HeimatGemeinde>
			<HeimatStrasse><![CDATA[Taubengasse 38]]></HeimatStrasse>
			<HeimatNation>A</HeimatNation>
				<ZugangCode>10</ZugangCode>
				<ZugangDatum>17062008</ZugangDatum>
			<ZugangMaStgCode>1</ZugangMaStgCode>
			<ZugangMaStgDatum>13072012</ZugangMaStgDatum>
				<Ausstellungsstaat>A</Ausstellungsstaat>
			<BeginnDatum>01092012</BeginnDatum>
			<BeendigungsDatum>30062014</BeendigungsDatum>
			<Ausbildungssemester>4</Ausbildungssemester>
			<StudStatusCode>3</StudStatusCode>
			<BerufstaetigkeitCode>10</BerufstaetigkeitCode>
					<StandortCode>14</StandortCode>
				<BMWFWfoerderrelevant>J</BMWFWfoerderrelevant>
		</StudentIn>
		<StudentIn>
			<PersKz>1210269012</PersKz>
			<OrgFormCode>2</OrgFormCode>
			<GeburtsDatum>18071990</GeburtsDatum>
			<Geschlecht>W</Geschlecht>
			<SVNR>1891180790</SVNR>
			<StaatsangehoerigkeitCode>A</StaatsangehoerigkeitCode>
			<HeimatPLZ>1160</HeimatPLZ>
			<HeimatGemeinde>Wien</HeimatGemeinde>
			<HeimatStrasse><![CDATA[Thaliastraße 79/33]]></HeimatStrasse>
			<HeimatNation>A</HeimatNation>
				<ZugangCode>10</ZugangCode>
				<ZugangDatum>30062009</ZugangDatum>
			<ZugangMaStgCode>1</ZugangMaStgCode>
			<ZugangMaStgDatum>13072012</ZugangMaStgDatum>
				<Ausstellungsstaat>A</Ausstellungsstaat>
			<BeginnDatum>01092012</BeginnDatum>
			<BeendigungsDatum>30062014</BeendigungsDatum>
			<Ausbildungssemester>4</Ausbildungssemester>
			<StudStatusCode>3</StudStatusCode>
			<BerufstaetigkeitCode>7</BerufstaetigkeitCode>
					<StandortCode>14</StandortCode>
				<BMWFWfoerderrelevant>J</BMWFWfoerderrelevant>
		</StudentIn>
		<StudentIn>
			<PersKz>1210269013</PersKz>
			<OrgFormCode>2</OrgFormCode>
			<GeburtsDatum>05041991</GeburtsDatum>
			<Geschlecht>W</Geschlecht>
			<SVNR>2505050491</SVNR>
			<StaatsangehoerigkeitCode>A</StaatsangehoerigkeitCode>
			<HeimatPLZ>2620</HeimatPLZ>
			<HeimatGemeinde>Neunkirchen</HeimatGemeinde>
			<HeimatStrasse><![CDATA[Schoellerstraße 14/5]]></HeimatStrasse>
			<HeimatNation>A</HeimatNation>
				<ZugangCode>9</ZugangCode>
				<ZugangDatum>10062009</ZugangDatum>
			<ZugangMaStgCode>1</ZugangMaStgCode>
			<ZugangMaStgDatum>13072012</ZugangMaStgDatum>
				<Ausstellungsstaat>A</Ausstellungsstaat>
			<BeginnDatum>01092012</BeginnDatum>
			<BeendigungsDatum>30062014</BeendigungsDatum>
			<Ausbildungssemester>4</Ausbildungssemester>
			<StudStatusCode>3</StudStatusCode>
			<BerufstaetigkeitCode>0</BerufstaetigkeitCode>
					<StandortCode>14</StandortCode>
				<BMWFWfoerderrelevant>J</BMWFWfoerderrelevant>
		</StudentIn>
		<StudentIn>
			<PersKz>1210269014</PersKz>
			<OrgFormCode>2</OrgFormCode>
			<GeburtsDatum>12081991</GeburtsDatum>
			<Geschlecht>W</Geschlecht>
			<SVNR>3057120891</SVNR>
			<StaatsangehoerigkeitCode>A</StaatsangehoerigkeitCode>
			<HeimatPLZ>8020</HeimatPLZ>
			<HeimatGemeinde>Graz</HeimatGemeinde>
			<HeimatStrasse><![CDATA[Zweiglgasse 16]]></HeimatStrasse>
			<HeimatNation>A</HeimatNation>
				<ZugangCode>9</ZugangCode>
				<ZugangDatum>25062009</ZugangDatum>
			<ZugangMaStgCode>1</ZugangMaStgCode>
			<ZugangMaStgDatum>13072012</ZugangMaStgDatum>
				<Ausstellungsstaat>A</Ausstellungsstaat>
			<BeginnDatum>01092012</BeginnDatum>
			<BeendigungsDatum>08092014</BeendigungsDatum>
			<Ausbildungssemester>4</Ausbildungssemester>
			<StudStatusCode>3</StudStatusCode>
			<BerufstaetigkeitCode>7</BerufstaetigkeitCode>
					<StandortCode>14</StandortCode>
				<BMWFWfoerderrelevant>J</BMWFWfoerderrelevant>
		</StudentIn>
		<StudentIn>
			<PersKz>1210269016</PersKz>
			<OrgFormCode>2</OrgFormCode>
			<GeburtsDatum>09101960</GeburtsDatum>
			<Geschlecht>W</Geschlecht>
			<SVNR>5105091060</SVNR>
			<StaatsangehoerigkeitCode>A</StaatsangehoerigkeitCode>
			<HeimatPLZ>7304</HeimatPLZ>
			<HeimatGemeinde>Großwarasdorf</HeimatGemeinde>
			<HeimatStrasse><![CDATA[Lorenz Bogovich Gasse 20]]></HeimatStrasse>
			<HeimatNation>A</HeimatNation>
				<ZugangCode>10</ZugangCode>
				<ZugangDatum>08061978</ZugangDatum>
			<ZugangMaStgCode>9</ZugangMaStgCode>
			<ZugangMaStgDatum>02071985</ZugangMaStgDatum>
				<Ausstellungsstaat>A</Ausstellungsstaat>
			<BeginnDatum>01092012</BeginnDatum>
			<BeendigungsDatum>01092014</BeendigungsDatum>
			<Ausbildungssemester>4</Ausbildungssemester>
			<StudStatusCode>3</StudStatusCode>
			<BerufstaetigkeitCode>6</BerufstaetigkeitCode>
					<StandortCode>14</StandortCode>
				<BMWFWfoerderrelevant>J</BMWFWfoerderrelevant>
		</StudentIn>
		<StudentIn>
			<PersKz>1210269017</PersKz>
			<OrgFormCode>2</OrgFormCode>
			<GeburtsDatum>24061980</GeburtsDatum>
			<Geschlecht>W</Geschlecht>
			<SVNR>1536240680</SVNR>
			<StaatsangehoerigkeitCode>A</StaatsangehoerigkeitCode>
			<HeimatPLZ>8230</HeimatPLZ>
			<HeimatGemeinde>Hartberg</HeimatGemeinde>
			<HeimatStrasse><![CDATA[Penzendorf 65]]></HeimatStrasse>
			<HeimatNation>A</HeimatNation>
				<ZugangCode>10</ZugangCode>
				<ZugangDatum>23061998</ZugangDatum>
			<ZugangMaStgCode>9</ZugangMaStgCode>
			<ZugangMaStgDatum>05022004</ZugangMaStgDatum>
				<Ausstellungsstaat>A</Ausstellungsstaat>
			<BeginnDatum>01092012</BeginnDatum>
			<BeendigungsDatum>30062014</BeendigungsDatum>
			<Ausbildungssemester>4</Ausbildungssemester>
			<StudStatusCode>3</StudStatusCode>
			<BerufstaetigkeitCode>0</BerufstaetigkeitCode>
					<StandortCode>14</StandortCode>
				<BMWFWfoerderrelevant>J</BMWFWfoerderrelevant>
		</StudentIn>
		<StudentIn>
			<PersKz>1210269018</PersKz>
			<OrgFormCode>2</OrgFormCode>
			<GeburtsDatum>21041989</GeburtsDatum>
			<Geschlecht>W</Geschlecht>
			<SVNR>4183210489</SVNR>
			<StaatsangehoerigkeitCode>A</StaatsangehoerigkeitCode>
			<HeimatPLZ>8333</HeimatPLZ>
			<HeimatGemeinde>Riegersburg</HeimatGemeinde>
			<HeimatStrasse><![CDATA[Grub I / 10]]></HeimatStrasse>
			<HeimatNation>A</HeimatNation>
				<ZugangCode>10</ZugangCode>
				<ZugangDatum>05062008</ZugangDatum>
			<ZugangMaStgCode>1</ZugangMaStgCode>
			<ZugangMaStgDatum>19102012</ZugangMaStgDatum>
				<Ausstellungsstaat>A</Ausstellungsstaat>
			<BeginnDatum>19102012</BeginnDatum>
			<BeendigungsDatum>08092014</BeendigungsDatum>
			<Ausbildungssemester>4</Ausbildungssemester>
			<StudStatusCode>3</StudStatusCode>
			<BerufstaetigkeitCode>7</BerufstaetigkeitCode>
					<StandortCode>14</StandortCode>
				<BMWFWfoerderrelevant>J</BMWFWfoerderrelevant>
		</StudentIn>
		<StudentIn>
			<PersKz>1210269019</PersKz>
			<OrgFormCode>2</OrgFormCode>
			<GeburtsDatum>03021988</GeburtsDatum>
			<Geschlecht>W</Geschlecht>
			<SVNR>2555030288</SVNR>
			<StaatsangehoerigkeitCode>A</StaatsangehoerigkeitCode>
			<HeimatPLZ>8225</HeimatPLZ>
			<HeimatGemeinde>Pöllau</HeimatGemeinde>
			<HeimatStrasse><![CDATA[Schönau 21]]></HeimatStrasse>
			<HeimatNation>A</HeimatNation>
				<ZugangCode>18</ZugangCode>
				<ZugangDatum>05092009</ZugangDatum>
			<ZugangMaStgCode>1</ZugangMaStgCode>
			<ZugangMaStgDatum>13072012</ZugangMaStgDatum>
				<Ausstellungsstaat>A</Ausstellungsstaat>
			<BeginnDatum>01092012</BeginnDatum>
			<BeendigungsDatum>01092014</BeendigungsDatum>
			<Ausbildungssemester>4</Ausbildungssemester>
			<StudStatusCode>3</StudStatusCode>
			<BerufstaetigkeitCode>3</BerufstaetigkeitCode>
					<StandortCode>14</StandortCode>
				<BMWFWfoerderrelevant>J</BMWFWfoerderrelevant>
		</StudentIn>
		<StudentIn>
			<PersKz>1210269020</PersKz>
			<OrgFormCode>2</OrgFormCode>
			<GeburtsDatum>24051991</GeburtsDatum>
			<Geschlecht>W</Geschlecht>
			<SVNR>3368240591</SVNR>
			<StaatsangehoerigkeitCode>A</StaatsangehoerigkeitCode>
			<HeimatPLZ>8062</HeimatPLZ>
			<HeimatGemeinde>Kumberg</HeimatGemeinde>
			<HeimatStrasse><![CDATA[Richterweg 24]]></HeimatStrasse>
			<HeimatNation>A</HeimatNation>
				<ZugangCode>10</ZugangCode>
				<ZugangDatum>15062009</ZugangDatum>
			<ZugangMaStgCode>1</ZugangMaStgCode>
			<ZugangMaStgDatum>13072012</ZugangMaStgDatum>
				<Ausstellungsstaat>A</Ausstellungsstaat>
			<BeginnDatum>01092012</BeginnDatum>
			<BeendigungsDatum>01072014</BeendigungsDatum>
			<Ausbildungssemester>4</Ausbildungssemester>
			<StudStatusCode>3</StudStatusCode>
			<BerufstaetigkeitCode>0</BerufstaetigkeitCode>
					<StandortCode>14</StandortCode>
				<BMWFWfoerderrelevant>J</BMWFWfoerderrelevant>
		</StudentIn>
		<StudentIn>
			<PersKz>1210269021</PersKz>
			<OrgFormCode>2</OrgFormCode>
			<GeburtsDatum>19011988</GeburtsDatum>
			<Geschlecht>W</Geschlecht>
			<SVNR>2535190188</SVNR>
			<StaatsangehoerigkeitCode>A</StaatsangehoerigkeitCode>
			<HeimatPLZ>8010</HeimatPLZ>
			<HeimatGemeinde>Graz</HeimatGemeinde>
			<HeimatStrasse><![CDATA[Leonhardstraße 100a 38]]></HeimatStrasse>
			<HeimatNation>A</HeimatNation>
				<ZugangCode>14</ZugangCode>
				<ZugangDatum>17062008</ZugangDatum>
			<ZugangMaStgCode>5</ZugangMaStgCode>
			<ZugangMaStgDatum>16082012</ZugangMaStgDatum>
				<Ausstellungsstaat>A</Ausstellungsstaat>
			<BeginnDatum>01092012</BeginnDatum>
			<BeendigungsDatum>01092014</BeendigungsDatum>
			<Ausbildungssemester>4</Ausbildungssemester>
			<StudStatusCode>3</StudStatusCode>
			<BerufstaetigkeitCode>7</BerufstaetigkeitCode>
					<StandortCode>14</StandortCode>
				<BMWFWfoerderrelevant>J</BMWFWfoerderrelevant>
		</StudentIn>
		<StudentIn>
			<PersKz>1210269023</PersKz>
			<OrgFormCode>2</OrgFormCode>
			<GeburtsDatum>27121988</GeburtsDatum>
			<Geschlecht>W</Geschlecht>
			<SVNR>3584271288</SVNR>
			<StaatsangehoerigkeitCode>A</StaatsangehoerigkeitCode>
			<HeimatPLZ>8042</HeimatPLZ>
			<HeimatGemeinde>Graz</HeimatGemeinde>
			<HeimatStrasse><![CDATA[St. Peter-Hauptstraße 112A, 3]]></HeimatStrasse>
			<HeimatNation>A</HeimatNation>
				<ZugangCode>10</ZugangCode>
				<ZugangDatum>18062008</ZugangDatum>
			<ZugangMaStgCode>5</ZugangMaStgCode>
			<ZugangMaStgDatum>30102012</ZugangMaStgDatum>
				<Ausstellungsstaat>A</Ausstellungsstaat>
			<BeginnDatum>30102012</BeginnDatum>
			<BeendigungsDatum>01092014</BeendigungsDatum>
			<Ausbildungssemester>4</Ausbildungssemester>
			<StudStatusCode>3</StudStatusCode>
			<BerufstaetigkeitCode>0</BerufstaetigkeitCode>
					<StandortCode>14</StandortCode>
				<BMWFWfoerderrelevant>J</BMWFWfoerderrelevant>
		</StudentIn>
		<StudentIn>
			<PersKz>1210269024</PersKz>
			<OrgFormCode>2</OrgFormCode>
			<GeburtsDatum>29021988</GeburtsDatum>
			<Geschlecht>M</Geschlecht>
			<SVNR>1678290288</SVNR>
			<StaatsangehoerigkeitCode>A</StaatsangehoerigkeitCode>
			<HeimatPLZ>1080</HeimatPLZ>
			<HeimatGemeinde>Wien</HeimatGemeinde>
			<HeimatStrasse><![CDATA[Florianigasse 21/3]]></HeimatStrasse>
			<HeimatNation>A</HeimatNation>
				<ZugangCode>12</ZugangCode>
				<ZugangDatum>04062008</ZugangDatum>
			<ZugangMaStgCode>1</ZugangMaStgCode>
			<ZugangMaStgDatum>09072012</ZugangMaStgDatum>
				<Ausstellungsstaat>A</Ausstellungsstaat>
			<BeginnDatum>01092012</BeginnDatum>
			<BeendigungsDatum>30062014</BeendigungsDatum>
			<Ausbildungssemester>4</Ausbildungssemester>
			<StudStatusCode>3</StudStatusCode>
			<BerufstaetigkeitCode>6</BerufstaetigkeitCode>
					<StandortCode>14</StandortCode>
				<BMWFWfoerderrelevant>J</BMWFWfoerderrelevant>
		</StudentIn>
		<StudentIn>
			<PersKz>1210269025</PersKz>
			<OrgFormCode>2</OrgFormCode>
			<GeburtsDatum>05041987</GeburtsDatum>
			<Geschlecht>M</Geschlecht>
			<SVNR>3710050487</SVNR>
			<StaatsangehoerigkeitCode>A</StaatsangehoerigkeitCode>
			<HeimatPLZ>8301</HeimatPLZ>
			<HeimatGemeinde>Laßnitzhöhe</HeimatGemeinde>
			<HeimatStrasse><![CDATA[Greimelweg 21]]></HeimatStrasse>
			<HeimatNation>A</HeimatNation>
				<ZugangCode>10</ZugangCode>
				<ZugangDatum>05032007</ZugangDatum>
			<ZugangMaStgCode>1</ZugangMaStgCode>
			<ZugangMaStgDatum>13072012</ZugangMaStgDatum>
				<Ausstellungsstaat>A</Ausstellungsstaat>
			<BeginnDatum>01092012</BeginnDatum>
			<Ausbildungssemester>50</Ausbildungssemester>
			<StudStatusCode>2</StudStatusCode>
			<BerufstaetigkeitCode>0</BerufstaetigkeitCode>
					<StandortCode>14</StandortCode>
				<BMWFWfoerderrelevant>J</BMWFWfoerderrelevant>
		</StudentIn>
		<StudentIn>
			<PersKz>1210269026</PersKz>
			<OrgFormCode>2</OrgFormCode>
			<GeburtsDatum>02011989</GeburtsDatum>
			<Geschlecht>M</Geschlecht>
			<SVNR>3298020189</SVNR>
			<StaatsangehoerigkeitCode>A</StaatsangehoerigkeitCode>
			<HeimatPLZ>4950</HeimatPLZ>
			<HeimatGemeinde>Altheim</HeimatGemeinde>
			<HeimatStrasse><![CDATA[Bahnhofstraße 3]]></HeimatStrasse>
			<HeimatNation>A</HeimatNation>
				<ZugangCode>13</ZugangCode>
				<ZugangDatum>19062008</ZugangDatum>
			<ZugangMaStgCode>1</ZugangMaStgCode>
			<ZugangMaStgDatum>13072012</ZugangMaStgDatum>
				<Ausstellungsstaat>A</Ausstellungsstaat>
			<BeginnDatum>01092012</BeginnDatum>
			<BeendigungsDatum>08092014</BeendigungsDatum>
			<Ausbildungssemester>4</Ausbildungssemester>
			<StudStatusCode>3</StudStatusCode>
			<BerufstaetigkeitCode>0</BerufstaetigkeitCode>
					<StandortCode>14</StandortCode>
				<BMWFWfoerderrelevant>J</BMWFWfoerderrelevant>
		</StudentIn>
		<StudentIn>
			<PersKz>1210269027</PersKz>
			<OrgFormCode>2</OrgFormCode>
			<GeburtsDatum>17021989</GeburtsDatum>
			<Geschlecht>W</Geschlecht>
			<SVNR>3354170289</SVNR>
			<StaatsangehoerigkeitCode>A</StaatsangehoerigkeitCode>
			<HeimatPLZ>7031</HeimatPLZ>
			<HeimatGemeinde>Krensdorf</HeimatGemeinde>
			<HeimatStrasse><![CDATA[Hauptstraße 14]]></HeimatStrasse>
			<HeimatNation>A</HeimatNation>
				<ZugangCode>14</ZugangCode>
				<ZugangDatum>16062008</ZugangDatum>
			<ZugangMaStgCode>1</ZugangMaStgCode>
			<ZugangMaStgDatum>13072012</ZugangMaStgDatum>
				<Ausstellungsstaat>A</Ausstellungsstaat>
			<BeginnDatum>01092012</BeginnDatum>
			<BeendigungsDatum>01092014</BeendigungsDatum>
			<Ausbildungssemester>4</Ausbildungssemester>
			<StudStatusCode>3</StudStatusCode>
			<BerufstaetigkeitCode>7</BerufstaetigkeitCode>
					<StandortCode>14</StandortCode>
				<BMWFWfoerderrelevant>J</BMWFWfoerderrelevant>
		</StudentIn>
		<StudentIn>
			<PersKz>1210269028</PersKz>
			<OrgFormCode>2</OrgFormCode>
			<GeburtsDatum>22091989</GeburtsDatum>
			<Geschlecht>W</Geschlecht>
			<SVNR>3160220989</SVNR>
			<StaatsangehoerigkeitCode>A</StaatsangehoerigkeitCode>
			<HeimatPLZ>7432</HeimatPLZ>
			<HeimatGemeinde>Oberschützen</HeimatGemeinde>
			<HeimatStrasse><![CDATA[Pinkafelder Straße 10/16]]></HeimatStrasse>
			<HeimatNation>A</HeimatNation>
				<ZugangCode>9</ZugangCode>
				<ZugangDatum>02062008</ZugangDatum>
			<ZugangMaStgCode>5</ZugangMaStgCode>
			<ZugangMaStgDatum>24102012</ZugangMaStgDatum>
				<Ausstellungsstaat>A</Ausstellungsstaat>
			<BeginnDatum>24102012</BeginnDatum>
			<Ausbildungssemester>50</Ausbildungssemester>
			<StudStatusCode>1</StudStatusCode>
			<BerufstaetigkeitCode>0</BerufstaetigkeitCode>
					<StandortCode>14</StandortCode>
				<BMWFWfoerderrelevant>J</BMWFWfoerderrelevant>
		</StudentIn>
		<StudentIn>
			<PersKz>1210269029</PersKz>
			<OrgFormCode>2</OrgFormCode>
			<GeburtsDatum>12021987</GeburtsDatum>
			<Geschlecht>W</Geschlecht>
			<SVNR>4827120287</SVNR>
			<StaatsangehoerigkeitCode>A</StaatsangehoerigkeitCode>
			<HeimatPLZ>8010</HeimatPLZ>
			<HeimatGemeinde>Graz</HeimatGemeinde>
			<HeimatStrasse><![CDATA[Körösistraße 56/3/18]]></HeimatStrasse>
			<HeimatNation>A</HeimatNation>
				<ZugangCode>14</ZugangCode>
				<ZugangDatum>05062007</ZugangDatum>
			<ZugangMaStgCode>3</ZugangMaStgCode>
			<ZugangMaStgDatum>19102012</ZugangMaStgDatum>
				<Ausstellungsstaat>A</Ausstellungsstaat>
			<BeginnDatum>19102012</BeginnDatum>
			<BeendigungsDatum>16092014</BeendigungsDatum>
			<Ausbildungssemester>4</Ausbildungssemester>
			<StudStatusCode>3</StudStatusCode>
			<BerufstaetigkeitCode>10</BerufstaetigkeitCode>
					<StandortCode>14</StandortCode>
				<BMWFWfoerderrelevant>J</BMWFWfoerderrelevant>
		</StudentIn>
		<StudentIn>
			<PersKz>1210269031</PersKz>
			<OrgFormCode>2</OrgFormCode>
			<GeburtsDatum>23071991</GeburtsDatum>
			<Geschlecht>W</Geschlecht>
			<SVNR>5212230791</SVNR>
			<StaatsangehoerigkeitCode>A</StaatsangehoerigkeitCode>
			<HeimatPLZ>8223</HeimatPLZ>
			<HeimatGemeinde>Stubenberg</HeimatGemeinde>
			<HeimatStrasse><![CDATA[Stubenberg am See 135]]></HeimatStrasse>
			<HeimatNation>A</HeimatNation>
				<ZugangCode>10</ZugangCode>
				<ZugangDatum>24062009</ZugangDatum>
			<ZugangMaStgCode>1</ZugangMaStgCode>
			<ZugangMaStgDatum>13072012</ZugangMaStgDatum>
				<Ausstellungsstaat>A</Ausstellungsstaat>
			<BeginnDatum>01092012</BeginnDatum>
			<BeendigungsDatum>01072014</BeendigungsDatum>
			<Ausbildungssemester>4</Ausbildungssemester>
			<StudStatusCode>3</StudStatusCode>
			<BerufstaetigkeitCode>0</BerufstaetigkeitCode>
					<StandortCode>14</StandortCode>
				<BMWFWfoerderrelevant>J</BMWFWfoerderrelevant>
		</StudentIn>
		<StudentIn>
			<PersKz>1210269032</PersKz>
			<OrgFormCode>2</OrgFormCode>
			<GeburtsDatum>02061984</GeburtsDatum>
			<Geschlecht>W</Geschlecht>
			<SVNR>3003020684</SVNR>
			<StaatsangehoerigkeitCode>A</StaatsangehoerigkeitCode>
			<HeimatPLZ>9433</HeimatPLZ>
			<HeimatGemeinde>St. Andrä</HeimatGemeinde>
			<HeimatStrasse><![CDATA[Winkling Nord 46]]></HeimatStrasse>
			<HeimatNation>A</HeimatNation>
				<ZugangCode>18</ZugangCode>
				<ZugangDatum>05072008</ZugangDatum>
			<ZugangMaStgCode>1</ZugangMaStgCode>
			<ZugangMaStgDatum>16102012</ZugangMaStgDatum>
				<Ausstellungsstaat>A</Ausstellungsstaat>
			<BeginnDatum>16102012</BeginnDatum>
			<Ausbildungssemester>50</Ausbildungssemester>
			<StudStatusCode>1</StudStatusCode>
			<BerufstaetigkeitCode>7</BerufstaetigkeitCode>
					<StandortCode>14</StandortCode>
				<BMWFWfoerderrelevant>J</BMWFWfoerderrelevant>
		</StudentIn>
		<StudentIn>
			<PersKz>1210269033</PersKz>
			<OrgFormCode>2</OrgFormCode>
			<GeburtsDatum>03121980</GeburtsDatum>
			<Geschlecht>M</Geschlecht>
			<SVNR>2205031280</SVNR>
			<StaatsangehoerigkeitCode>A</StaatsangehoerigkeitCode>
			<HeimatPLZ>6900</HeimatPLZ>
			<HeimatGemeinde>Bregenz</HeimatGemeinde>
			<HeimatStrasse><![CDATA[Arlbergstraße 58/Top 57]]></HeimatStrasse>
			<HeimatNation>A</HeimatNation>
				<ZugangCode>14</ZugangCode>
				<ZugangDatum>20062001</ZugangDatum>
			<ZugangMaStgCode>1</ZugangMaStgCode>
			<ZugangMaStgDatum>13072012</ZugangMaStgDatum>
				<Ausstellungsstaat>A</Ausstellungsstaat>
			<BeginnDatum>01092012</BeginnDatum>
			<Ausbildungssemester>50</Ausbildungssemester>
			<StudStatusCode>1</StudStatusCode>
			<BerufstaetigkeitCode>9</BerufstaetigkeitCode>
					<StandortCode>14</StandortCode>
				<BMWFWfoerderrelevant>J</BMWFWfoerderrelevant>
		</StudentIn>
		<StudentIn>
			<PersKz>1210269034</PersKz>
			<OrgFormCode>2</OrgFormCode>
			<GeburtsDatum>24111989</GeburtsDatum>
			<Geschlecht>W</Geschlecht>
			<SVNR>2268241189</SVNR>
			<StaatsangehoerigkeitCode>A</StaatsangehoerigkeitCode>
			<HeimatPLZ>2873</HeimatPLZ>
			<HeimatGemeinde>Feistritz am Wechsel</HeimatGemeinde>
			<HeimatStrasse><![CDATA[Feistritz 284]]></HeimatStrasse>
			<HeimatNation>A</HeimatNation>
				<ZugangCode>10</ZugangCode>
				<ZugangDatum>19062009</ZugangDatum>
			<ZugangMaStgCode>1</ZugangMaStgCode>
			<ZugangMaStgDatum>16102012</ZugangMaStgDatum>
				<Ausstellungsstaat>A</Ausstellungsstaat>
			<BeginnDatum>16102012</BeginnDatum>
			<Ausbildungssemester>50</Ausbildungssemester>
			<StudStatusCode>1</StudStatusCode>
			<BerufstaetigkeitCode>0</BerufstaetigkeitCode>
					<StandortCode>14</StandortCode>
				<BMWFWfoerderrelevant>J</BMWFWfoerderrelevant>
		</StudentIn>
		<StudentIn>
			<PersKz>1310269001</PersKz>
			<OrgFormCode>2</OrgFormCode>
			<GeburtsDatum>30041977</GeburtsDatum>
			<Geschlecht>W</Geschlecht>
			<SVNR>1228300477</SVNR>
			<StaatsangehoerigkeitCode>A</StaatsangehoerigkeitCode>
			<HeimatPLZ>2803</HeimatPLZ>
			<HeimatGemeinde>Schwarzenbach</HeimatGemeinde>
			<HeimatStrasse><![CDATA[Markt 3]]></HeimatStrasse>
			<HeimatNation>A</HeimatNation>
				<ZugangCode>13</ZugangCode>
				<ZugangDatum>07061996</ZugangDatum>
			<ZugangMaStgCode>4</ZugangMaStgCode>
			<ZugangMaStgDatum>26081999</ZugangMaStgDatum>
				<Ausstellungsstaat>A</Ausstellungsstaat>
			<BeginnDatum>01092013</BeginnDatum>
			<Ausbildungssemester>1</Ausbildungssemester>
			<StudStatusCode>2</StudStatusCode>
			<BerufstaetigkeitCode>0</BerufstaetigkeitCode>
					<StandortCode>14</StandortCode>
				<BMWFWfoerderrelevant>J</BMWFWfoerderrelevant>
		</StudentIn>
		<StudentIn>
			<PersKz>1310269003</PersKz>
			<OrgFormCode>2</OrgFormCode>
			<GeburtsDatum>17121980</GeburtsDatum>
			<Geschlecht>W</Geschlecht>
			<SVNR>2946171280</SVNR>
			<StaatsangehoerigkeitCode>A</StaatsangehoerigkeitCode>
			<HeimatPLZ>8072</HeimatPLZ>
			<HeimatGemeinde>Fernitz</HeimatGemeinde>
			<HeimatStrasse><![CDATA[Am Klostergrund 54]]></HeimatStrasse>
			<HeimatNation>A</HeimatNation>
				<ZugangCode>9</ZugangCode>
				<ZugangDatum>23061999</ZugangDatum>
			<ZugangMaStgCode>7</ZugangMaStgCode>
			<ZugangMaStgDatum>09112007</ZugangMaStgDatum>
				<Ausstellungsstaat>A</Ausstellungsstaat>
			<BeginnDatum>01092013</BeginnDatum>
			<Ausbildungssemester>3</Ausbildungssemester>
			<StudStatusCode>1</StudStatusCode>
			<BerufstaetigkeitCode>6</BerufstaetigkeitCode>
					<StandortCode>14</StandortCode>
				<BMWFWfoerderrelevant>J</BMWFWfoerderrelevant>
		</StudentIn>
		<StudentIn>
			<PersKz>1310269004</PersKz>
			<OrgFormCode>2</OrgFormCode>
			<GeburtsDatum>07031983</GeburtsDatum>
			<Geschlecht>W</Geschlecht>
			<SVNR>1812070383</SVNR>
			<StaatsangehoerigkeitCode>A</StaatsangehoerigkeitCode>
			<HeimatPLZ>1040</HeimatPLZ>
			<HeimatGemeinde>Wien</HeimatGemeinde>
			<HeimatStrasse><![CDATA[Waltergasse 3/5]]></HeimatStrasse>
			<HeimatNation>A</HeimatNation>
				<ZugangCode>9</ZugangCode>
				<ZugangDatum>20062001</ZugangDatum>
			<ZugangMaStgCode>9</ZugangMaStgCode>
			<ZugangMaStgDatum>17112008</ZugangMaStgDatum>
				<Ausstellungsstaat>A</Ausstellungsstaat>
			<BeginnDatum>01092013</BeginnDatum>
			<BeendigungsDatum>30072014</BeendigungsDatum>
			<Ausbildungssemester>1</Ausbildungssemester>
			<StudStatusCode>4</StudStatusCode>
			<BerufstaetigkeitCode>9</BerufstaetigkeitCode>
					<StandortCode>14</StandortCode>
				<BMWFWfoerderrelevant>J</BMWFWfoerderrelevant>
		</StudentIn>
		<StudentIn>
			<PersKz>1310269005</PersKz>
			<OrgFormCode>2</OrgFormCode>
			<GeburtsDatum>06061984</GeburtsDatum>
			<Geschlecht>W</Geschlecht>
			<SVNR>4216060684</SVNR>
			<StaatsangehoerigkeitCode>A</StaatsangehoerigkeitCode>
			<HeimatPLZ>1150</HeimatPLZ>
			<HeimatGemeinde>Wien</HeimatGemeinde>
			<HeimatStrasse><![CDATA[Goldschlagstraße 83-85/3/12]]></HeimatStrasse>
			<HeimatNation>A</HeimatNation>
				<ZugangCode>18</ZugangCode>
				<ZugangDatum>28092004</ZugangDatum>
			<ZugangMaStgCode>1</ZugangMaStgCode>
			<ZugangMaStgDatum>28062010</ZugangMaStgDatum>
				<Ausstellungsstaat>A</Ausstellungsstaat>
			<BeginnDatum>01092013</BeginnDatum>
			<Ausbildungssemester>3</Ausbildungssemester>
			<StudStatusCode>1</StudStatusCode>
			<BerufstaetigkeitCode>6</BerufstaetigkeitCode>
					<StandortCode>14</StandortCode>
				<BMWFWfoerderrelevant>J</BMWFWfoerderrelevant>
		</StudentIn>
		<StudentIn>
			<PersKz>1310269006</PersKz>
			<OrgFormCode>2</OrgFormCode>
			<GeburtsDatum>28021988</GeburtsDatum>
			<Geschlecht>W</Geschlecht>
			<SVNR>4185280288</SVNR>
			<StaatsangehoerigkeitCode>A</StaatsangehoerigkeitCode>
			<HeimatPLZ>8010</HeimatPLZ>
			<HeimatGemeinde>Graz</HeimatGemeinde>
			<HeimatStrasse><![CDATA[Rechbauerstrasse 32/1/6]]></HeimatStrasse>
			<HeimatNation>A</HeimatNation>
				<ZugangCode>9</ZugangCode>
				<ZugangDatum>26062006</ZugangDatum>
			<ZugangMaStgCode>1</ZugangMaStgCode>
			<ZugangMaStgDatum>23072010</ZugangMaStgDatum>
				<Ausstellungsstaat>A</Ausstellungsstaat>
			<BeginnDatum>01092013</BeginnDatum>
			<Ausbildungssemester>3</Ausbildungssemester>
			<StudStatusCode>1</StudStatusCode>
			<BerufstaetigkeitCode>7</BerufstaetigkeitCode>
					<StandortCode>14</StandortCode>
				<BMWFWfoerderrelevant>J</BMWFWfoerderrelevant>
		</StudentIn>
		<StudentIn>
			<PersKz>1310269007</PersKz>
			<OrgFormCode>2</OrgFormCode>
			<GeburtsDatum>19031984</GeburtsDatum>
			<Geschlecht>W</Geschlecht>
			<SVNR>1518190384</SVNR>
			<StaatsangehoerigkeitCode>A</StaatsangehoerigkeitCode>
			<HeimatPLZ>1020</HeimatPLZ>
			<HeimatGemeinde>Wien</HeimatGemeinde>
			<HeimatStrasse><![CDATA[Handelskai 214/14/23]]></HeimatStrasse>
			<HeimatNation>A</HeimatNation>
				<ZugangCode>9</ZugangCode>
				<ZugangDatum>10062002</ZugangDatum>
			<ZugangMaStgCode>9</ZugangMaStgCode>
			<ZugangMaStgDatum>27102010</ZugangMaStgDatum>
				<Ausstellungsstaat>A</Ausstellungsstaat>
			<BeginnDatum>01092013</BeginnDatum>
			<Ausbildungssemester>3</Ausbildungssemester>
			<StudStatusCode>1</StudStatusCode>
			<BerufstaetigkeitCode>9</BerufstaetigkeitCode>
					<StandortCode>14</StandortCode>
				<BMWFWfoerderrelevant>J</BMWFWfoerderrelevant>
		</StudentIn>
		<StudentIn>
			<PersKz>1310269008</PersKz>
			<OrgFormCode>2</OrgFormCode>
			<GeburtsDatum>08081983</GeburtsDatum>
			<Geschlecht>M</Geschlecht>
			<SVNR>2707080883</SVNR>
			<StaatsangehoerigkeitCode>A</StaatsangehoerigkeitCode>
			<HeimatPLZ>7521</HeimatPLZ>
			<HeimatGemeinde>Eberau</HeimatGemeinde>
			<HeimatStrasse><![CDATA[Gaas 104]]></HeimatStrasse>
			<HeimatNation>A</HeimatNation>
				<ZugangCode>10</ZugangCode>
				<ZugangDatum>15062001</ZugangDatum>
			<ZugangMaStgCode>9</ZugangMaStgCode>
			<ZugangMaStgDatum>14042011</ZugangMaStgDatum>
				<Ausstellungsstaat>A</Ausstellungsstaat>
			<BeginnDatum>01092013</BeginnDatum>
			<Ausbildungssemester>3</Ausbildungssemester>
			<StudStatusCode>1</StudStatusCode>
			<BerufstaetigkeitCode>7</BerufstaetigkeitCode>
					<StandortCode>14</StandortCode>
				<BMWFWfoerderrelevant>J</BMWFWfoerderrelevant>
		</StudentIn>
		<StudentIn>
			<PersKz>1310269009</PersKz>
			<OrgFormCode>2</OrgFormCode>
			<GeburtsDatum>29051990</GeburtsDatum>
			<Geschlecht>W</Geschlecht>
			<SVNR>4150290590</SVNR>
			<StaatsangehoerigkeitCode>BSH</StaatsangehoerigkeitCode>
			<HeimatPLZ>7540</HeimatPLZ>
			<HeimatGemeinde>Moschendorf</HeimatGemeinde>
			<HeimatStrasse><![CDATA[Moschendorf 112/2a]]></HeimatStrasse>
			<HeimatNation>A</HeimatNation>
				<ZugangCode>10</ZugangCode>
				<ZugangDatum>13102009</ZugangDatum>
			<ZugangMaStgCode>1</ZugangMaStgCode>
			<ZugangMaStgDatum>19062012</ZugangMaStgDatum>
				<Ausstellungsstaat>A</Ausstellungsstaat>
			<BeginnDatum>01092013</BeginnDatum>
			<Ausbildungssemester>3</Ausbildungssemester>
			<StudStatusCode>1</StudStatusCode>
			<BerufstaetigkeitCode>0</BerufstaetigkeitCode>
					<StandortCode>14</StandortCode>
				<BMWFWfoerderrelevant>J</BMWFWfoerderrelevant>
		</StudentIn>
		<StudentIn>
			<PersKz>1310269011</PersKz>
			<OrgFormCode>2</OrgFormCode>
			<GeburtsDatum>04071987</GeburtsDatum>
			<Geschlecht>M</Geschlecht>
			<SVNR>2329040787</SVNR>
			<StaatsangehoerigkeitCode>A</StaatsangehoerigkeitCode>
			<HeimatPLZ>7201</HeimatPLZ>
			<HeimatGemeinde>Neudörfl</HeimatGemeinde>
			<HeimatStrasse><![CDATA[Pöttschingerstraße 1/1/5]]></HeimatStrasse>
			<HeimatNation>A</HeimatNation>
				<ZugangCode>17</ZugangCode>
				<ZugangDatum>06102008</ZugangDatum>
			<ZugangMaStgCode>1</ZugangMaStgCode>
			<ZugangMaStgDatum>05072012</ZugangMaStgDatum>
				<Ausstellungsstaat>A</Ausstellungsstaat>
			<BeginnDatum>01092013</BeginnDatum>
			<Ausbildungssemester>3</Ausbildungssemester>
			<StudStatusCode>1</StudStatusCode>
			<BerufstaetigkeitCode>7</BerufstaetigkeitCode>
					<StandortCode>14</StandortCode>
				<BMWFWfoerderrelevant>J</BMWFWfoerderrelevant>
		</StudentIn>
		<StudentIn>
			<PersKz>1310269012</PersKz>
			<OrgFormCode>2</OrgFormCode>
			<GeburtsDatum>24021961</GeburtsDatum>
			<Geschlecht>W</Geschlecht>
			<SVNR>1145240261</SVNR>
			<StaatsangehoerigkeitCode>A</StaatsangehoerigkeitCode>
			<HeimatPLZ>2482</HeimatPLZ>
			<HeimatGemeinde>Münchendorf</HeimatGemeinde>
			<HeimatStrasse><![CDATA[Franz Fürst Gasse 2/3/7]]></HeimatStrasse>
			<HeimatNation>A</HeimatNation>
				<ZugangCode>14</ZugangCode>
				<ZugangDatum>19061980</ZugangDatum>
			<ZugangMaStgCode>1</ZugangMaStgCode>
			<ZugangMaStgDatum>13072012</ZugangMaStgDatum>
				<Ausstellungsstaat>A</Ausstellungsstaat>
			<BeginnDatum>01092013</BeginnDatum>
			<Ausbildungssemester>2</Ausbildungssemester>
			<StudStatusCode>2</StudStatusCode>
			<BerufstaetigkeitCode>3</BerufstaetigkeitCode>
					<StandortCode>14</StandortCode>
				<BMWFWfoerderrelevant>J</BMWFWfoerderrelevant>
		</StudentIn>
		<StudentIn>
			<PersKz>1310269013</PersKz>
			<OrgFormCode>2</OrgFormCode>
			<GeburtsDatum>14081991</GeburtsDatum>
			<Geschlecht>W</Geschlecht>
			<SVNR>2817140891</SVNR>
			<StaatsangehoerigkeitCode>A</StaatsangehoerigkeitCode>
			<HeimatPLZ>2103</HeimatPLZ>
			<HeimatGemeinde>Langenzersdorf</HeimatGemeinde>
			<HeimatStrasse><![CDATA[Gärtnergasse 6/2/2]]></HeimatStrasse>
			<HeimatNation>A</HeimatNation>
				<ZugangCode>9</ZugangCode>
				<ZugangDatum>03062009</ZugangDatum>
			<ZugangMaStgCode>1</ZugangMaStgCode>
			<ZugangMaStgDatum>13072012</ZugangMaStgDatum>
				<Ausstellungsstaat>A</Ausstellungsstaat>
			<BeginnDatum>01092013</BeginnDatum>
			<Ausbildungssemester>3</Ausbildungssemester>
			<StudStatusCode>1</StudStatusCode>
			<BerufstaetigkeitCode>10</BerufstaetigkeitCode>
					<StandortCode>14</StandortCode>
				<BMWFWfoerderrelevant>J</BMWFWfoerderrelevant>
		</StudentIn>
		<StudentIn>
			<PersKz>1310269014</PersKz>
			<OrgFormCode>2</OrgFormCode>
			<GeburtsDatum>26041990</GeburtsDatum>
			<Geschlecht>W</Geschlecht>
			<SVNR>3621260490</SVNR>
			<StaatsangehoerigkeitCode>A</StaatsangehoerigkeitCode>
			<HeimatPLZ>1150</HeimatPLZ>
			<HeimatGemeinde>Wien</HeimatGemeinde>
			<HeimatStrasse><![CDATA[Auf der Schmelz]]></HeimatStrasse>
			<HeimatNation>A</HeimatNation>
				<ZugangCode>10</ZugangCode>
				<ZugangDatum>16062009</ZugangDatum>
			<ZugangMaStgCode>5</ZugangMaStgCode>
			<ZugangMaStgDatum>22082012</ZugangMaStgDatum>
				<Ausstellungsstaat>A</Ausstellungsstaat>
			<BeginnDatum>01092013</BeginnDatum>
			<Ausbildungssemester>3</Ausbildungssemester>
			<StudStatusCode>1</StudStatusCode>
			<BerufstaetigkeitCode>7</BerufstaetigkeitCode>
					<StandortCode>14</StandortCode>
				<BMWFWfoerderrelevant>J</BMWFWfoerderrelevant>
		</StudentIn>
		<StudentIn>
			<PersKz>1310269015</PersKz>
			<OrgFormCode>2</OrgFormCode>
			<GeburtsDatum>08031990</GeburtsDatum>
			<Geschlecht>W</Geschlecht>
			<SVNR>4687080390</SVNR>
			<StaatsangehoerigkeitCode>A</StaatsangehoerigkeitCode>
			<HeimatPLZ>8093</HeimatPLZ>
			<HeimatGemeinde>Sankt Peter am Ottersbach</HeimatGemeinde>
			<HeimatStrasse><![CDATA[Perbersdorf 59]]></HeimatStrasse>
			<HeimatNation>A</HeimatNation>
				<ZugangCode>10</ZugangCode>
				<ZugangDatum>20062008</ZugangDatum>
			<ZugangMaStgCode>5</ZugangMaStgCode>
			<ZugangMaStgDatum>14032013</ZugangMaStgDatum>
				<Ausstellungsstaat>A</Ausstellungsstaat>
			<BeginnDatum>01092013</BeginnDatum>
			<Ausbildungssemester>3</Ausbildungssemester>
			<StudStatusCode>1</StudStatusCode>
			<BerufstaetigkeitCode>6</BerufstaetigkeitCode>
					<StandortCode>14</StandortCode>
				<BMWFWfoerderrelevant>J</BMWFWfoerderrelevant>
		</StudentIn>
		<StudentIn>
			<PersKz>1310269016</PersKz>
			<OrgFormCode>2</OrgFormCode>
			<GeburtsDatum>15061988</GeburtsDatum>
			<Geschlecht>W</Geschlecht>
			<SVNR>2148150688</SVNR>
			<StaatsangehoerigkeitCode>A</StaatsangehoerigkeitCode>
			<HeimatPLZ>8042</HeimatPLZ>
			<HeimatGemeinde>Graz</HeimatGemeinde>
			<HeimatStrasse><![CDATA[Peterstalstrasse 32]]></HeimatStrasse>
			<HeimatNation>A</HeimatNation>
				<ZugangCode>14</ZugangCode>
				<ZugangDatum>19062007</ZugangDatum>
			<ZugangMaStgCode>5</ZugangMaStgCode>
			<ZugangMaStgDatum>11062013</ZugangMaStgDatum>
				<Ausstellungsstaat>A</Ausstellungsstaat>
			<BeginnDatum>01092013</BeginnDatum>
			<Ausbildungssemester>3</Ausbildungssemester>
			<StudStatusCode>1</StudStatusCode>
			<BerufstaetigkeitCode>7</BerufstaetigkeitCode>
					<StandortCode>14</StandortCode>
				<BMWFWfoerderrelevant>J</BMWFWfoerderrelevant>
		</StudentIn>
		<StudentIn>
			<PersKz>1310269017</PersKz>
			<OrgFormCode>2</OrgFormCode>
			<GeburtsDatum>09111987</GeburtsDatum>
			<Geschlecht>W</Geschlecht>
			<SVNR>1747091187</SVNR>
			<StaatsangehoerigkeitCode>A</StaatsangehoerigkeitCode>
			<HeimatPLZ>2451</HeimatPLZ>
			<HeimatGemeinde>Au am Leithaberge</HeimatGemeinde>
			<HeimatStrasse><![CDATA[Jagdgasse 18]]></HeimatStrasse>
			<HeimatNation>A</HeimatNation>
				<ZugangCode>13</ZugangCode>
				<ZugangDatum>13062007</ZugangDatum>
			<ZugangMaStgCode>5</ZugangMaStgCode>
			<ZugangMaStgDatum>04062013</ZugangMaStgDatum>
				<Ausstellungsstaat>A</Ausstellungsstaat>
			<BeginnDatum>01092013</BeginnDatum>
			<Ausbildungssemester>3</Ausbildungssemester>
			<StudStatusCode>1</StudStatusCode>
			<BerufstaetigkeitCode>10</BerufstaetigkeitCode>
					<StandortCode>14</StandortCode>
				<BMWFWfoerderrelevant>J</BMWFWfoerderrelevant>
		</StudentIn>
		<StudentIn>
			<PersKz>1310269018</PersKz>
			<OrgFormCode>2</OrgFormCode>
			<GeburtsDatum>25101989</GeburtsDatum>
			<Geschlecht>W</Geschlecht>
			<SVNR>3469251089</SVNR>
			<StaatsangehoerigkeitCode>A</StaatsangehoerigkeitCode>
			<HeimatPLZ>2831</HeimatPLZ>
			<HeimatGemeinde>Scheiblingkirchen</HeimatGemeinde>
			<HeimatStrasse><![CDATA[Wehrgasse 139]]></HeimatStrasse>
			<HeimatNation>A</HeimatNation>
				<ZugangCode>14</ZugangCode>
				<ZugangDatum>06062009</ZugangDatum>
			<ZugangMaStgCode>1</ZugangMaStgCode>
			<ZugangMaStgDatum>17062013</ZugangMaStgDatum>
				<Ausstellungsstaat>A</Ausstellungsstaat>
			<BeginnDatum>01092013</BeginnDatum>
			<Ausbildungssemester>3</Ausbildungssemester>
			<StudStatusCode>1</StudStatusCode>
			<BerufstaetigkeitCode>7</BerufstaetigkeitCode>
					<StandortCode>14</StandortCode>
				<BMWFWfoerderrelevant>J</BMWFWfoerderrelevant>
		</StudentIn>
		<StudentIn>
			<PersKz>1310269020</PersKz>
			<OrgFormCode>2</OrgFormCode>
			<GeburtsDatum>23031991</GeburtsDatum>
			<Geschlecht>W</Geschlecht>
			<SVNR>4538230391</SVNR>
			<StaatsangehoerigkeitCode>A</StaatsangehoerigkeitCode>
			<HeimatPLZ>7131</HeimatPLZ>
			<HeimatGemeinde>Halbturn</HeimatGemeinde>
			<HeimatStrasse><![CDATA[Neugasse 3]]></HeimatStrasse>
			<HeimatNation>A</HeimatNation>
				<ZugangCode>9</ZugangCode>
				<ZugangDatum>17062009</ZugangDatum>
			<ZugangMaStgCode>1</ZugangMaStgCode>
			<ZugangMaStgDatum>17062013</ZugangMaStgDatum>
				<Ausstellungsstaat>A</Ausstellungsstaat>
			<BeginnDatum>01092013</BeginnDatum>
			<Ausbildungssemester>3</Ausbildungssemester>
			<StudStatusCode>1</StudStatusCode>
			<BerufstaetigkeitCode>7</BerufstaetigkeitCode>
					<StandortCode>14</StandortCode>
				<BMWFWfoerderrelevant>J</BMWFWfoerderrelevant>
		</StudentIn>
		<StudentIn>
			<PersKz>1310269021</PersKz>
			<OrgFormCode>2</OrgFormCode>
			<GeburtsDatum>02021977</GeburtsDatum>
			<Geschlecht>W</Geschlecht>
			<SVNR>1612020277</SVNR>
			<StaatsangehoerigkeitCode>A</StaatsangehoerigkeitCode>
			<HeimatPLZ>8271</HeimatPLZ>
			<HeimatGemeinde>Bad Waltersdorf</HeimatGemeinde>
			<HeimatStrasse><![CDATA[Haller 58]]></HeimatStrasse>
			<HeimatNation>A</HeimatNation>
				<ZugangCode>13</ZugangCode>
				<ZugangDatum>30051997</ZugangDatum>
			<ZugangMaStgCode>1</ZugangMaStgCode>
			<ZugangMaStgDatum>17062013</ZugangMaStgDatum>
				<Ausstellungsstaat>A</Ausstellungsstaat>
			<BeginnDatum>01092013</BeginnDatum>
			<Ausbildungssemester>3</Ausbildungssemester>
			<StudStatusCode>1</StudStatusCode>
			<BerufstaetigkeitCode>0</BerufstaetigkeitCode>
					<StandortCode>14</StandortCode>
				<BMWFWfoerderrelevant>J</BMWFWfoerderrelevant>
		</StudentIn>
		<StudentIn>
			<PersKz>1310269022</PersKz>
			<OrgFormCode>2</OrgFormCode>
			<GeburtsDatum>27071990</GeburtsDatum>
			<Geschlecht>W</Geschlecht>
			<SVNR>2621270790</SVNR>
			<StaatsangehoerigkeitCode>A</StaatsangehoerigkeitCode>
			<HeimatPLZ>1230</HeimatPLZ>
			<HeimatGemeinde>Wien</HeimatGemeinde>
			<HeimatStrasse><![CDATA[Am Spiegeln 51]]></HeimatStrasse>
			<HeimatNation>A</HeimatNation>
				<ZugangCode>14</ZugangCode>
				<ZugangDatum>10062009</ZugangDatum>
			<ZugangMaStgCode>1</ZugangMaStgCode>
			<ZugangMaStgDatum>18062013</ZugangMaStgDatum>
				<Ausstellungsstaat>A</Ausstellungsstaat>
			<BeginnDatum>01092013</BeginnDatum>
			<Ausbildungssemester>3</Ausbildungssemester>
			<StudStatusCode>1</StudStatusCode>
			<BerufstaetigkeitCode>7</BerufstaetigkeitCode>
					<StandortCode>14</StandortCode>
				<BMWFWfoerderrelevant>J</BMWFWfoerderrelevant>
		</StudentIn>
		<StudentIn>
			<PersKz>1310269023</PersKz>
			<OrgFormCode>2</OrgFormCode>
			<GeburtsDatum>11091980</GeburtsDatum>
			<Geschlecht>W</Geschlecht>
			<SVNR>2677110980</SVNR>
			<StaatsangehoerigkeitCode>A</StaatsangehoerigkeitCode>
			<HeimatPLZ>7400</HeimatPLZ>
			<HeimatGemeinde>Oberwart</HeimatGemeinde>
			<HeimatStrasse><![CDATA[Drumling 81]]></HeimatStrasse>
			<HeimatNation>A</HeimatNation>
				<ZugangCode>18</ZugangCode>
				<ZugangDatum>12032010</ZugangDatum>
			<ZugangMaStgCode>1</ZugangMaStgCode>
			<ZugangMaStgDatum>18062013</ZugangMaStgDatum>
				<Ausstellungsstaat>A</Ausstellungsstaat>
			<BeginnDatum>01092013</BeginnDatum>
			<Ausbildungssemester>3</Ausbildungssemester>
			<StudStatusCode>1</StudStatusCode>
			<BerufstaetigkeitCode>7</BerufstaetigkeitCode>
					<StandortCode>14</StandortCode>
				<BMWFWfoerderrelevant>J</BMWFWfoerderrelevant>
		</StudentIn>
		<StudentIn>
			<PersKz>1310269024</PersKz>
			<OrgFormCode>2</OrgFormCode>
			<GeburtsDatum>04101990</GeburtsDatum>
			<Geschlecht>W</Geschlecht>
			<SVNR>2365041090</SVNR>
			<StaatsangehoerigkeitCode>A</StaatsangehoerigkeitCode>
			<HeimatPLZ>1210</HeimatPLZ>
			<HeimatGemeinde>Wien</HeimatGemeinde>
			<HeimatStrasse><![CDATA[Skraupstraße 24/30/43]]></HeimatStrasse>
			<HeimatNation>A</HeimatNation>
				<ZugangCode>9</ZugangCode>
				<ZugangDatum>17062009</ZugangDatum>
			<ZugangMaStgCode>1</ZugangMaStgCode>
			<ZugangMaStgDatum>18062013</ZugangMaStgDatum>
				<Ausstellungsstaat>A</Ausstellungsstaat>
			<BeginnDatum>01092013</BeginnDatum>
			<Ausbildungssemester>3</Ausbildungssemester>
			<StudStatusCode>1</StudStatusCode>
			<BerufstaetigkeitCode>0</BerufstaetigkeitCode>
					<StandortCode>14</StandortCode>
				<BMWFWfoerderrelevant>J</BMWFWfoerderrelevant>
		</StudentIn>
		<StudentIn>
			<PersKz>1310269025</PersKz>
			<OrgFormCode>2</OrgFormCode>
			<GeburtsDatum>20091990</GeburtsDatum>
			<Geschlecht>W</Geschlecht>
			<SVNR>4929200990</SVNR>
			<StaatsangehoerigkeitCode>A</StaatsangehoerigkeitCode>
			<HeimatPLZ>8182</HeimatPLZ>
			<HeimatGemeinde>Puch bei Weiz</HeimatGemeinde>
			<HeimatStrasse><![CDATA[Elz 86]]></HeimatStrasse>
			<HeimatNation>A</HeimatNation>
				<ZugangCode>14</ZugangCode>
				<ZugangDatum>24062010</ZugangDatum>
			<ZugangMaStgCode>1</ZugangMaStgCode>
			<ZugangMaStgDatum>18062013</ZugangMaStgDatum>
				<Ausstellungsstaat>A</Ausstellungsstaat>
			<BeginnDatum>01092013</BeginnDatum>
			<Ausbildungssemester>3</Ausbildungssemester>
			<StudStatusCode>1</StudStatusCode>
			<BerufstaetigkeitCode>7</BerufstaetigkeitCode>
					<StandortCode>14</StandortCode>
				<BMWFWfoerderrelevant>J</BMWFWfoerderrelevant>
		</StudentIn>
		<StudentIn>
			<PersKz>1310269026</PersKz>
			<OrgFormCode>2</OrgFormCode>
			<GeburtsDatum>21011978</GeburtsDatum>
			<Geschlecht>W</Geschlecht>
			<SVNR>1044210178</SVNR>
			<StaatsangehoerigkeitCode>A</StaatsangehoerigkeitCode>
			<HeimatPLZ>9155</HeimatPLZ>
			<HeimatGemeinde>Neuhaus</HeimatGemeinde>
			<HeimatStrasse><![CDATA[Schwabegg 47]]></HeimatStrasse>
			<HeimatNation>A</HeimatNation>
				<ZugangCode>14</ZugangCode>
				<ZugangDatum>18061997</ZugangDatum>
			<ZugangMaStgCode>1</ZugangMaStgCode>
			<ZugangMaStgDatum>18062013</ZugangMaStgDatum>
				<Ausstellungsstaat>A</Ausstellungsstaat>
			<BeginnDatum>01092013</BeginnDatum>
			<Ausbildungssemester>3</Ausbildungssemester>
			<StudStatusCode>2</StudStatusCode>
			<BerufstaetigkeitCode>0</BerufstaetigkeitCode>
					<StandortCode>14</StandortCode>
				<BMWFWfoerderrelevant>J</BMWFWfoerderrelevant>
		</StudentIn>
		<StudentIn>
			<PersKz>1310269027</PersKz>
			<OrgFormCode>2</OrgFormCode>
			<GeburtsDatum>21071989</GeburtsDatum>
			<Geschlecht>W</Geschlecht>
			<SVNR>4330210789</SVNR>
			<StaatsangehoerigkeitCode>CRO</StaatsangehoerigkeitCode>
			<HeimatPLZ>9413</HeimatPLZ>
			<HeimatGemeinde>St. Gertraud</HeimatGemeinde>
			<HeimatStrasse><![CDATA[St. Gertraud 55]]></HeimatStrasse>
			<HeimatNation>A</HeimatNation>
				<ZugangCode>10</ZugangCode>
				<ZugangDatum>16062008</ZugangDatum>
			<ZugangMaStgCode>1</ZugangMaStgCode>
			<ZugangMaStgDatum>18062013</ZugangMaStgDatum>
				<Ausstellungsstaat>A</Ausstellungsstaat>
			<BeginnDatum>01092013</BeginnDatum>
			<Ausbildungssemester>3</Ausbildungssemester>
			<StudStatusCode>1</StudStatusCode>
			<BerufstaetigkeitCode>10</BerufstaetigkeitCode>
					<StandortCode>14</StandortCode>
				<BMWFWfoerderrelevant>J</BMWFWfoerderrelevant>
		</StudentIn>
		<StudentIn>
			<PersKz>1310269028</PersKz>
			<OrgFormCode>2</OrgFormCode>
			<GeburtsDatum>11041991</GeburtsDatum>
			<Geschlecht>W</Geschlecht>
			<SVNR>4282110491</SVNR>
			<StaatsangehoerigkeitCode>A</StaatsangehoerigkeitCode>
			<HeimatPLZ>7503</HeimatPLZ>
			<HeimatGemeinde>Jabing</HeimatGemeinde>
			<HeimatStrasse><![CDATA[Am Mühlweg 5]]></HeimatStrasse>
			<HeimatNation>A</HeimatNation>
				<ZugangCode>14</ZugangCode>
				<ZugangDatum>28052010</ZugangDatum>
			<ZugangMaStgCode>1</ZugangMaStgCode>
			<ZugangMaStgDatum>19062013</ZugangMaStgDatum>
				<Ausstellungsstaat>A</Ausstellungsstaat>
			<BeginnDatum>01092013</BeginnDatum>
			<Ausbildungssemester>3</Ausbildungssemester>
			<StudStatusCode>1</StudStatusCode>
			<BerufstaetigkeitCode>0</BerufstaetigkeitCode>
					<StandortCode>14</StandortCode>
				<BMWFWfoerderrelevant>J</BMWFWfoerderrelevant>
		</StudentIn>
		<StudentIn>
			<PersKz>1310269029</PersKz>
			<OrgFormCode>2</OrgFormCode>
			<GeburtsDatum>13051992</GeburtsDatum>
			<Geschlecht>W</Geschlecht>
			<SVNR>3898130592</SVNR>
			<StaatsangehoerigkeitCode>A</StaatsangehoerigkeitCode>
			<HeimatPLZ>8262</HeimatPLZ>
			<HeimatGemeinde>Nestelbach im Ilztal</HeimatGemeinde>
			<HeimatStrasse><![CDATA[Mutzenfeld 2]]></HeimatStrasse>
			<HeimatNation>A</HeimatNation>
				<ZugangCode>11</ZugangCode>
				<ZugangDatum>28062010</ZugangDatum>
			<ZugangMaStgCode>1</ZugangMaStgCode>
			<ZugangMaStgDatum>19062013</ZugangMaStgDatum>
				<Ausstellungsstaat>A</Ausstellungsstaat>
			<BeginnDatum>01092013</BeginnDatum>
			<Ausbildungssemester>3</Ausbildungssemester>
			<StudStatusCode>1</StudStatusCode>
			<BerufstaetigkeitCode>7</BerufstaetigkeitCode>
					<StandortCode>14</StandortCode>
				<BMWFWfoerderrelevant>J</BMWFWfoerderrelevant>
		</StudentIn>
		<StudentIn>
			<PersKz>1310269030</PersKz>
			<OrgFormCode>2</OrgFormCode>
			<GeburtsDatum>20091989</GeburtsDatum>
			<Geschlecht>W</Geschlecht>
			<SVNR>5436200989</SVNR>
			<StaatsangehoerigkeitCode>A</StaatsangehoerigkeitCode>
			<HeimatPLZ>8501</HeimatPLZ>
			<HeimatGemeinde>Lieboch</HeimatGemeinde>
			<HeimatStrasse><![CDATA[Grabenstraße 5/4]]></HeimatStrasse>
			<HeimatNation>A</HeimatNation>
				<ZugangCode>13</ZugangCode>
				<ZugangDatum>05062009</ZugangDatum>
			<ZugangMaStgCode>1</ZugangMaStgCode>
			<ZugangMaStgDatum>19062013</ZugangMaStgDatum>
				<Ausstellungsstaat>A</Ausstellungsstaat>
			<BeginnDatum>01092013</BeginnDatum>
			<Ausbildungssemester>3</Ausbildungssemester>
			<StudStatusCode>1</StudStatusCode>
			<BerufstaetigkeitCode>2</BerufstaetigkeitCode>
					<StandortCode>14</StandortCode>
				<BMWFWfoerderrelevant>J</BMWFWfoerderrelevant>
		</StudentIn>
		<StudentIn>
			<PersKz>1310269031</PersKz>
			<OrgFormCode>2</OrgFormCode>
			<GeburtsDatum>24091984</GeburtsDatum>
			<Geschlecht>W</Geschlecht>
			<SVNR>4232240984</SVNR>
			<StaatsangehoerigkeitCode>A</StaatsangehoerigkeitCode>
			<HeimatPLZ>2620</HeimatPLZ>
			<HeimatGemeinde>Neunkirchen</HeimatGemeinde>
			<HeimatStrasse><![CDATA[Ortsstraße 68]]></HeimatStrasse>
			<HeimatNation>A</HeimatNation>
				<ZugangCode>9</ZugangCode>
				<ZugangDatum>13062003</ZugangDatum>
			<ZugangMaStgCode>1</ZugangMaStgCode>
			<ZugangMaStgDatum>19062013</ZugangMaStgDatum>
				<Ausstellungsstaat>A</Ausstellungsstaat>
			<BeginnDatum>01092013</BeginnDatum>
			<Ausbildungssemester>3</Ausbildungssemester>
			<StudStatusCode>1</StudStatusCode>
			<BerufstaetigkeitCode>7</BerufstaetigkeitCode>
					<StandortCode>14</StandortCode>
				<BMWFWfoerderrelevant>J</BMWFWfoerderrelevant>
		</StudentIn>
		<StudentIn>
			<PersKz>1310269032</PersKz>
			<OrgFormCode>2</OrgFormCode>
			<GeburtsDatum>10071986</GeburtsDatum>
			<Geschlecht>W</Geschlecht>
			<SVNR>3479100786</SVNR>
			<StaatsangehoerigkeitCode>A</StaatsangehoerigkeitCode>
			<HeimatPLZ>8243</HeimatPLZ>
			<HeimatGemeinde>Pinggau</HeimatGemeinde>
			<HeimatStrasse><![CDATA[Hauptplatz 14]]></HeimatStrasse>
			<HeimatNation>A</HeimatNation>
				<ZugangCode>4</ZugangCode>
				<ZugangDatum>11082011</ZugangDatum>
			<ZugangMaStgCode>1</ZugangMaStgCode>
			<ZugangMaStgDatum>21062013</ZugangMaStgDatum>
				<Ausstellungsstaat>A</Ausstellungsstaat>
			<BeginnDatum>01092013</BeginnDatum>
			<BeendigungsDatum>25082014</BeendigungsDatum>
			<Ausbildungssemester>2</Ausbildungssemester>
			<StudStatusCode>4</StudStatusCode>
			<BerufstaetigkeitCode>0</BerufstaetigkeitCode>
					<StandortCode>14</StandortCode>
				<BMWFWfoerderrelevant>J</BMWFWfoerderrelevant>
		</StudentIn>
		<StudentIn>
			<PersKz>1310269034</PersKz>
			<OrgFormCode>2</OrgFormCode>
			<GeburtsDatum>09031991</GeburtsDatum>
			<Geschlecht>W</Geschlecht>
			<SVNR>3249090391</SVNR>
			<StaatsangehoerigkeitCode>A</StaatsangehoerigkeitCode>
			<HeimatPLZ>8020</HeimatPLZ>
			<HeimatGemeinde>Graz</HeimatGemeinde>
			<HeimatStrasse><![CDATA[Alte Poststraße 82/14]]></HeimatStrasse>
			<HeimatNation>A</HeimatNation>
				<ZugangCode>10</ZugangCode>
				<ZugangDatum>16062009</ZugangDatum>
			<ZugangMaStgCode>3</ZugangMaStgCode>
			<ZugangMaStgDatum>15102013</ZugangMaStgDatum>
				<Ausstellungsstaat>A</Ausstellungsstaat>
			<BeginnDatum>15102013</BeginnDatum>
			<Ausbildungssemester>3</Ausbildungssemester>
			<StudStatusCode>1</StudStatusCode>
			<BerufstaetigkeitCode>10</BerufstaetigkeitCode>
					<StandortCode>14</StandortCode>
				<BMWFWfoerderrelevant>J</BMWFWfoerderrelevant>
		</StudentIn>
		<StudentIn>
			<PersKz>1310269035</PersKz>
			<OrgFormCode>2</OrgFormCode>
			<GeburtsDatum>22091991</GeburtsDatum>
			<Geschlecht>W</Geschlecht>
			<SVNR>5155220991</SVNR>
			<StaatsangehoerigkeitCode>A</StaatsangehoerigkeitCode>
			<HeimatPLZ>8230</HeimatPLZ>
			<HeimatGemeinde>Hartberg</HeimatGemeinde>
			<HeimatStrasse><![CDATA[Flattendorf 15]]></HeimatStrasse>
			<HeimatNation>A</HeimatNation>
				<ZugangCode>9</ZugangCode>
				<ZugangDatum>11062010</ZugangDatum>
			<ZugangMaStgCode>1</ZugangMaStgCode>
			<ZugangMaStgDatum>27092013</ZugangMaStgDatum>
				<Ausstellungsstaat>A</Ausstellungsstaat>
			<BeginnDatum>27092013</BeginnDatum>
			<Ausbildungssemester>3</Ausbildungssemester>
			<StudStatusCode>1</StudStatusCode>
			<BerufstaetigkeitCode>0</BerufstaetigkeitCode>
					<StandortCode>14</StandortCode>
				<BMWFWfoerderrelevant>J</BMWFWfoerderrelevant>
		</StudentIn>
		<StudentIn>
			<PersKz>1310269036</PersKz>
			<OrgFormCode>2</OrgFormCode>
			<GeburtsDatum>06081971</GeburtsDatum>
			<Geschlecht>W</Geschlecht>
			<SVNR>3965060871</SVNR>
			<StaatsangehoerigkeitCode>A</StaatsangehoerigkeitCode>
			<HeimatPLZ>7400</HeimatPLZ>
			<HeimatGemeinde>Oberwart</HeimatGemeinde>
			<HeimatStrasse><![CDATA[Raingasse 9b]]></HeimatStrasse>
			<HeimatNation>A</HeimatNation>
				<ZugangCode>9</ZugangCode>
				<ZugangDatum>15061989</ZugangDatum>
			<ZugangMaStgCode>3</ZugangMaStgCode>
			<ZugangMaStgDatum>03031992</ZugangMaStgDatum>
				<Ausstellungsstaat>A</Ausstellungsstaat>
			<BeginnDatum>01092013</BeginnDatum>
			<Ausbildungssemester>3</Ausbildungssemester>
			<StudStatusCode>1</StudStatusCode>
			<BerufstaetigkeitCode>7</BerufstaetigkeitCode>
					<StandortCode>14</StandortCode>
				<BMWFWfoerderrelevant>J</BMWFWfoerderrelevant>
		</StudentIn>
		<StudentIn>
			<PersKz>1310269037</PersKz>
			<OrgFormCode>2</OrgFormCode>
			<GeburtsDatum>25061972</GeburtsDatum>
			<Geschlecht>W</Geschlecht>
			<SVNR>1939250672</SVNR>
			<StaatsangehoerigkeitCode>A</StaatsangehoerigkeitCode>
			<HeimatPLZ>7431</HeimatPLZ>
			<HeimatGemeinde>Bad Tatzmannsdorf</HeimatGemeinde>
			<HeimatStrasse><![CDATA[Feldgasse 19/4]]></HeimatStrasse>
			<HeimatNation>A</HeimatNation>
				<ZugangCode>10</ZugangCode>
				<ZugangDatum>30051990</ZugangDatum>
			<ZugangMaStgCode>3</ZugangMaStgCode>
			<ZugangMaStgDatum>02031993</ZugangMaStgDatum>
				<Ausstellungsstaat>A</Ausstellungsstaat>
			<BeginnDatum>01092013</BeginnDatum>
			<Ausbildungssemester>3</Ausbildungssemester>
			<StudStatusCode>1</StudStatusCode>
			<BerufstaetigkeitCode>6</BerufstaetigkeitCode>
					<StandortCode>14</StandortCode>
				<BMWFWfoerderrelevant>J</BMWFWfoerderrelevant>
		</StudentIn>
		<StudentIn>
			<PersKz>1410269001</PersKz>
			<OrgFormCode>2</OrgFormCode>
			<GeburtsDatum>08011991</GeburtsDatum>
			<Geschlecht>W</Geschlecht>
			<SVNR>1883080191</SVNR>
			<StaatsangehoerigkeitCode>A</StaatsangehoerigkeitCode>
			<HeimatPLZ>1130</HeimatPLZ>
			<HeimatGemeinde>Wien</HeimatGemeinde>
			<HeimatStrasse><![CDATA[Egon-Schiele-Gasse 19]]></HeimatStrasse>
			<HeimatNation>A</HeimatNation>
				<ZugangCode>12</ZugangCode>
				<ZugangDatum>22062014</ZugangDatum>
			<ZugangMaStgCode>1</ZugangMaStgCode>
			<ZugangMaStgDatum>24062014</ZugangMaStgDatum>
				<Ausstellungsstaat>A</Ausstellungsstaat>
			<BeginnDatum>04092014</BeginnDatum>
			<Ausbildungssemester>1</Ausbildungssemester>
			<StudStatusCode>1</StudStatusCode>
			<BerufstaetigkeitCode>7</BerufstaetigkeitCode>
					<StandortCode>14</StandortCode>
				<BMWFWfoerderrelevant>J</BMWFWfoerderrelevant>
		</StudentIn>
		<StudentIn>
			<PersKz>1410269002</PersKz>
			<OrgFormCode>2</OrgFormCode>
			<GeburtsDatum>04031991</GeburtsDatum>
			<Geschlecht>W</Geschlecht>
			<SVNR>3373040391</SVNR>
			<StaatsangehoerigkeitCode>A</StaatsangehoerigkeitCode>
			<HeimatPLZ>2403</HeimatPLZ>
			<HeimatGemeinde>Scharndorf</HeimatGemeinde>
			<HeimatStrasse><![CDATA[Hauptstraße 43]]></HeimatStrasse>
			<HeimatNation>A</HeimatNation>
				<ZugangCode>14</ZugangCode>
				<ZugangDatum>04062010</ZugangDatum>
			<ZugangMaStgCode>1</ZugangMaStgCode>
			<ZugangMaStgDatum>24062014</ZugangMaStgDatum>
				<Ausstellungsstaat>A</Ausstellungsstaat>
			<BeginnDatum>04092014</BeginnDatum>
			<Ausbildungssemester>1</Ausbildungssemester>
			<StudStatusCode>1</StudStatusCode>
			<BerufstaetigkeitCode>7</BerufstaetigkeitCode>
					<StandortCode>14</StandortCode>
				<BMWFWfoerderrelevant>J</BMWFWfoerderrelevant>
		</StudentIn>
		<StudentIn>
			<PersKz>1410269003</PersKz>
			<OrgFormCode>2</OrgFormCode>
			<GeburtsDatum>28061975</GeburtsDatum>
			<Geschlecht>W</Geschlecht>
			<SVNR>3908280675</SVNR>
			<StaatsangehoerigkeitCode>A</StaatsangehoerigkeitCode>
			<HeimatPLZ>7341</HeimatPLZ>
			<HeimatGemeinde>Markt Sankt Martin</HeimatGemeinde>
			<HeimatStrasse><![CDATA[Landsee 224]]></HeimatStrasse>
			<HeimatNation>A</HeimatNation>
				<ZugangCode>10</ZugangCode>
				<ZugangDatum>18061993</ZugangDatum>
			<ZugangMaStgCode>7</ZugangMaStgCode>
			<ZugangMaStgDatum>14042000</ZugangMaStgDatum>
				<Ausstellungsstaat>A</Ausstellungsstaat>
			<BeginnDatum>11092014</BeginnDatum>
			<Ausbildungssemester>1</Ausbildungssemester>
			<StudStatusCode>1</StudStatusCode>
			<BerufstaetigkeitCode>10</BerufstaetigkeitCode>
					<StandortCode>14</StandortCode>
				<BMWFWfoerderrelevant>J</BMWFWfoerderrelevant>
		</StudentIn>
		<StudentIn>
			<PersKz>1410269004</PersKz>
			<OrgFormCode>2</OrgFormCode>
			<GeburtsDatum>14101990</GeburtsDatum>
			<Geschlecht>W</Geschlecht>
			<SVNR>2431141090</SVNR>
			<StaatsangehoerigkeitCode>A</StaatsangehoerigkeitCode>
			<HeimatPLZ>2460</HeimatPLZ>
			<HeimatGemeinde>Bruck an der Leitha</HeimatGemeinde>
			<HeimatStrasse><![CDATA[Alte Wiener Straße 28]]></HeimatStrasse>
			<HeimatNation>A</HeimatNation>
				<ZugangCode>9</ZugangCode>
				<ZugangDatum>16062009</ZugangDatum>
			<ZugangMaStgCode>1</ZugangMaStgCode>
			<ZugangMaStgDatum>12072012</ZugangMaStgDatum>
				<Ausstellungsstaat>A</Ausstellungsstaat>
			<BeginnDatum>11092014</BeginnDatum>
			<Ausbildungssemester>1</Ausbildungssemester>
			<StudStatusCode>1</StudStatusCode>
			<BerufstaetigkeitCode>7</BerufstaetigkeitCode>
					<StandortCode>14</StandortCode>
				<BMWFWfoerderrelevant>J</BMWFWfoerderrelevant>
		</StudentIn>
		<StudentIn>
			<PersKz>1410269005</PersKz>
			<OrgFormCode>2</OrgFormCode>
			<GeburtsDatum>21071988</GeburtsDatum>
			<Geschlecht>W</Geschlecht>
			<SVNR>1580210788</SVNR>
			<StaatsangehoerigkeitCode>A</StaatsangehoerigkeitCode>
			<HeimatPLZ>2231</HeimatPLZ>
			<HeimatGemeinde>Strasshof an der Nordbahn</HeimatGemeinde>
			<HeimatStrasse><![CDATA[Hauptstrasse 144/7]]></HeimatStrasse>
			<HeimatNation>A</HeimatNation>
				<ZugangCode>14</ZugangCode>
				<ZugangDatum>12062007</ZugangDatum>
			<ZugangMaStgCode>1</ZugangMaStgCode>
			<ZugangMaStgDatum>24072013</ZugangMaStgDatum>
				<Ausstellungsstaat>A</Ausstellungsstaat>
			<BeginnDatum>11092014</BeginnDatum>
			<Ausbildungssemester>1</Ausbildungssemester>
			<StudStatusCode>1</StudStatusCode>
			<BerufstaetigkeitCode>6</BerufstaetigkeitCode>
					<StandortCode>14</StandortCode>
				<BMWFWfoerderrelevant>J</BMWFWfoerderrelevant>
		</StudentIn>
		<StudentIn>
			<PersKz>1410269006</PersKz>
			<OrgFormCode>2</OrgFormCode>
			<GeburtsDatum>14051992</GeburtsDatum>
			<Geschlecht>W</Geschlecht>
			<SVNR>4353140592</SVNR>
			<StaatsangehoerigkeitCode>A</StaatsangehoerigkeitCode>
			<HeimatPLZ>7444</HeimatPLZ>
			<HeimatGemeinde>Klostermarienberg</HeimatGemeinde>
			<HeimatStrasse><![CDATA[Hauptstraße 1]]></HeimatStrasse>
			<HeimatNation>A</HeimatNation>
				<ZugangCode>14</ZugangCode>
				<ZugangDatum>06062011</ZugangDatum>
			<ZugangMaStgCode>1</ZugangMaStgCode>
			<ZugangMaStgDatum>24062014</ZugangMaStgDatum>
				<Ausstellungsstaat>A</Ausstellungsstaat>
			<BeginnDatum>11092014</BeginnDatum>
			<Ausbildungssemester>1</Ausbildungssemester>
			<StudStatusCode>1</StudStatusCode>
			<BerufstaetigkeitCode>7</BerufstaetigkeitCode>
					<StandortCode>14</StandortCode>
				<BMWFWfoerderrelevant>J</BMWFWfoerderrelevant>
		</StudentIn>
		<StudentIn>
			<PersKz>1410269007</PersKz>
			<OrgFormCode>2</OrgFormCode>
			<GeburtsDatum>16021968</GeburtsDatum>
			<Geschlecht>M</Geschlecht>
			<SVNR>5785160268</SVNR>
			<StaatsangehoerigkeitCode>A</StaatsangehoerigkeitCode>
			<HeimatPLZ>7471</HeimatPLZ>
			<HeimatGemeinde>Rechnitz</HeimatGemeinde>
			<HeimatStrasse><![CDATA[Mühlbachgasse 81]]></HeimatStrasse>
			<HeimatNation>A</HeimatNation>
				<ZugangCode>5</ZugangCode>
				<ZugangDatum>10071987</ZugangDatum>
			<ZugangMaStgCode>9</ZugangMaStgCode>
			<ZugangMaStgDatum>25012011</ZugangMaStgDatum>
				<Ausstellungsstaat>A</Ausstellungsstaat>
			<BeginnDatum>11092014</BeginnDatum>
			<Ausbildungssemester>1</Ausbildungssemester>
			<StudStatusCode>1</StudStatusCode>
			<BerufstaetigkeitCode>7</BerufstaetigkeitCode>
					<StandortCode>14</StandortCode>
				<BMWFWfoerderrelevant>J</BMWFWfoerderrelevant>
		</StudentIn>
		<StudentIn>
			<PersKz>1410269008</PersKz>
			<OrgFormCode>2</OrgFormCode>
			<GeburtsDatum>26051993</GeburtsDatum>
			<Geschlecht>W</Geschlecht>
			<SVNR>4702260593</SVNR>
			<StaatsangehoerigkeitCode>A</StaatsangehoerigkeitCode>
			<HeimatPLZ>7203</HeimatPLZ>
			<HeimatGemeinde>Wiesen</HeimatGemeinde>
			<HeimatStrasse><![CDATA[Hauptstraße 76]]></HeimatStrasse>
			<HeimatNation>A</HeimatNation>
				<ZugangCode>10</ZugangCode>
				<ZugangDatum>06062011</ZugangDatum>
			<ZugangMaStgCode>1</ZugangMaStgCode>
			<ZugangMaStgDatum>26062014</ZugangMaStgDatum>
				<Ausstellungsstaat>A</Ausstellungsstaat>
			<BeginnDatum>11092014</BeginnDatum>
			<Ausbildungssemester>1</Ausbildungssemester>
			<StudStatusCode>1</StudStatusCode>
			<BerufstaetigkeitCode>0</BerufstaetigkeitCode>
					<StandortCode>14</StandortCode>
				<BMWFWfoerderrelevant>J</BMWFWfoerderrelevant>
		</StudentIn>
		<StudentIn>
			<PersKz>1410269009</PersKz>
			<OrgFormCode>2</OrgFormCode>
			<GeburtsDatum>17051992</GeburtsDatum>
			<Geschlecht>W</Geschlecht>
			<SVNR>3002170592</SVNR>
			<StaatsangehoerigkeitCode>A</StaatsangehoerigkeitCode>
			<HeimatPLZ>8225</HeimatPLZ>
			<HeimatGemeinde>Pöllau</HeimatGemeinde>
			<HeimatStrasse><![CDATA[Hauptplatz 10]]></HeimatStrasse>
			<HeimatNation>A</HeimatNation>
				<ZugangCode>14</ZugangCode>
				<ZugangDatum>07062011</ZugangDatum>
			<ZugangMaStgCode>1</ZugangMaStgCode>
			<ZugangMaStgDatum>23062014</ZugangMaStgDatum>
				<Ausstellungsstaat>A</Ausstellungsstaat>
			<BeginnDatum>11092014</BeginnDatum>
			<Ausbildungssemester>1</Ausbildungssemester>
			<StudStatusCode>1</StudStatusCode>
			<BerufstaetigkeitCode>10</BerufstaetigkeitCode>
					<StandortCode>14</StandortCode>
				<BMWFWfoerderrelevant>J</BMWFWfoerderrelevant>
		</StudentIn>
		<StudentIn>
			<PersKz>1410269010</PersKz>
			<OrgFormCode>2</OrgFormCode>
			<GeburtsDatum>27081986</GeburtsDatum>
			<Geschlecht>M</Geschlecht>
			<SVNR>3839270886</SVNR>
			<StaatsangehoerigkeitCode>A</StaatsangehoerigkeitCode>
			<HeimatPLZ>1050</HeimatPLZ>
			<HeimatGemeinde>Wien</HeimatGemeinde>
			<HeimatStrasse><![CDATA[Wiedner Hauptstraße 100-102 1/19]]></HeimatStrasse>
			<HeimatNation>A</HeimatNation>
				<ZugangCode>12</ZugangCode>
				<ZugangDatum>03102006</ZugangDatum>
			<ZugangMaStgCode>2</ZugangMaStgCode>
			<ZugangMaStgDatum>07082013</ZugangMaStgDatum>
				<Ausstellungsstaat>D</Ausstellungsstaat>
			<BeginnDatum>11092014</BeginnDatum>
			<Ausbildungssemester>1</Ausbildungssemester>
			<StudStatusCode>1</StudStatusCode>
			<BerufstaetigkeitCode>6</BerufstaetigkeitCode>
					<StandortCode>14</StandortCode>
				<BMWFWfoerderrelevant>J</BMWFWfoerderrelevant>
		</StudentIn>
		<StudentIn>
			<PersKz>1410269011</PersKz>
			<OrgFormCode>2</OrgFormCode>
			<GeburtsDatum>21101989</GeburtsDatum>
			<Geschlecht>W</Geschlecht>
			<SVNR>4825211089</SVNR>
			<StaatsangehoerigkeitCode>A</StaatsangehoerigkeitCode>
			<HeimatPLZ>8330</HeimatPLZ>
			<HeimatGemeinde>Feldbach</HeimatGemeinde>
			<HeimatStrasse><![CDATA[Petersdorf 13]]></HeimatStrasse>
			<HeimatNation>A</HeimatNation>
				<ZugangCode>10</ZugangCode>
				<ZugangDatum>13062008</ZugangDatum>
			<ZugangMaStgCode>1</ZugangMaStgCode>
			<ZugangMaStgDatum>31102013</ZugangMaStgDatum>
				<Ausstellungsstaat>A</Ausstellungsstaat>
			<BeginnDatum>11092014</BeginnDatum>
			<Ausbildungssemester>1</Ausbildungssemester>
			<StudStatusCode>1</StudStatusCode>
			<BerufstaetigkeitCode>7</BerufstaetigkeitCode>
					<StandortCode>14</StandortCode>
				<BMWFWfoerderrelevant>J</BMWFWfoerderrelevant>
		</StudentIn>
		<StudentIn>
			<PersKz>1410269012</PersKz>
			<OrgFormCode>2</OrgFormCode>
			<GeburtsDatum>13011990</GeburtsDatum>
			<Geschlecht>W</Geschlecht>
			<SVNR>4622130190</SVNR>
			<StaatsangehoerigkeitCode>A</StaatsangehoerigkeitCode>
			<HeimatPLZ>8273</HeimatPLZ>
			<HeimatGemeinde>Ebersdorf</HeimatGemeinde>
			<HeimatStrasse><![CDATA[Ebersdorf 60]]></HeimatStrasse>
			<HeimatNation>A</HeimatNation>
				<ZugangCode>14</ZugangCode>
				<ZugangDatum>29062009</ZugangDatum>
			<ZugangMaStgCode>1</ZugangMaStgCode>
			<ZugangMaStgDatum>07032014</ZugangMaStgDatum>
				<Ausstellungsstaat>A</Ausstellungsstaat>
			<BeginnDatum>11092014</BeginnDatum>
			<Ausbildungssemester>1</Ausbildungssemester>
			<StudStatusCode>1</StudStatusCode>
			<BerufstaetigkeitCode>0</BerufstaetigkeitCode>
					<StandortCode>14</StandortCode>
				<BMWFWfoerderrelevant>J</BMWFWfoerderrelevant>
		</StudentIn>
		<StudentIn>
			<PersKz>1410269013</PersKz>
			<OrgFormCode>2</OrgFormCode>
			<GeburtsDatum>11111977</GeburtsDatum>
			<Geschlecht>W</Geschlecht>
			<SVNR>3860111177</SVNR>
			<StaatsangehoerigkeitCode>A</StaatsangehoerigkeitCode>
			<HeimatPLZ>2801</HeimatPLZ>
			<HeimatGemeinde>Katzelsdorf</HeimatGemeinde>
			<HeimatStrasse><![CDATA[Dorfgasse 4a]]></HeimatStrasse>
			<HeimatNation>A</HeimatNation>
				<ZugangCode>9</ZugangCode>
				<ZugangDatum>19061996</ZugangDatum>
			<ZugangMaStgCode>3</ZugangMaStgCode>
			<ZugangMaStgDatum>04102000</ZugangMaStgDatum>
				<Ausstellungsstaat>A</Ausstellungsstaat>
			<BeginnDatum>11092014</BeginnDatum>
			<Ausbildungssemester>1</Ausbildungssemester>
			<StudStatusCode>1</StudStatusCode>
			<BerufstaetigkeitCode>7</BerufstaetigkeitCode>
					<StandortCode>14</StandortCode>
				<BMWFWfoerderrelevant>J</BMWFWfoerderrelevant>
		</StudentIn>
		<StudentIn>
			<PersKz>1410269014</PersKz>
			<OrgFormCode>2</OrgFormCode>
			<GeburtsDatum>20021982</GeburtsDatum>
			<Geschlecht>W</Geschlecht>
			<SVNR>1493200282</SVNR>
			<StaatsangehoerigkeitCode>A</StaatsangehoerigkeitCode>
			<HeimatPLZ>2460</HeimatPLZ>
			<HeimatGemeinde>Bruckneudorf</HeimatGemeinde>
			<HeimatStrasse><![CDATA[Theißstr. 2/2]]></HeimatStrasse>
			<HeimatNation>A</HeimatNation>
				<ZugangCode>9</ZugangCode>
				<ZugangDatum>15062000</ZugangDatum>
			<ZugangMaStgCode>9</ZugangMaStgCode>
			<ZugangMaStgDatum>09072008</ZugangMaStgDatum>
				<Ausstellungsstaat>A</Ausstellungsstaat>
			<BeginnDatum>11092014</BeginnDatum>
			<Ausbildungssemester>1</Ausbildungssemester>
			<StudStatusCode>1</StudStatusCode>
			<BerufstaetigkeitCode>9</BerufstaetigkeitCode>
					<StandortCode>14</StandortCode>
				<BMWFWfoerderrelevant>J</BMWFWfoerderrelevant>
		</StudentIn>
		<StudentIn>
			<PersKz>1410269015</PersKz>
			<OrgFormCode>2</OrgFormCode>
			<GeburtsDatum>06021991</GeburtsDatum>
			<Geschlecht>W</Geschlecht>
			<SVNR>4643060291</SVNR>
			<StaatsangehoerigkeitCode>A</StaatsangehoerigkeitCode>
			<HeimatPLZ>2442</HeimatPLZ>
			<HeimatGemeinde>Ebreichsdorf</HeimatGemeinde>
			<HeimatStrasse><![CDATA[Hauptplatz 9/1]]></HeimatStrasse>
			<HeimatNation>A</HeimatNation>
				<ZugangCode>9</ZugangCode>
				<ZugangDatum>26062009</ZugangDatum>
			<ZugangMaStgCode>1</ZugangMaStgCode>
			<ZugangMaStgDatum>03072014</ZugangMaStgDatum>
				<Ausstellungsstaat>A</Ausstellungsstaat>
			<BeginnDatum>11092014</BeginnDatum>
			<Ausbildungssemester>1</Ausbildungssemester>
			<StudStatusCode>1</StudStatusCode>
			<BerufstaetigkeitCode>10</BerufstaetigkeitCode>
					<StandortCode>14</StandortCode>
				<BMWFWfoerderrelevant>J</BMWFWfoerderrelevant>
		</StudentIn>
		<StudentIn>
			<PersKz>1410269016</PersKz>
			<OrgFormCode>2</OrgFormCode>
			<GeburtsDatum>15031991</GeburtsDatum>
			<Geschlecht>W</Geschlecht>
			<SVNR>3551150391</SVNR>
			<StaatsangehoerigkeitCode>A</StaatsangehoerigkeitCode>
			<HeimatPLZ>8160</HeimatPLZ>
			<HeimatGemeinde>Weiz</HeimatGemeinde>
			<HeimatStrasse><![CDATA[Weizbergstraße 16/5]]></HeimatStrasse>
			<HeimatNation>A</HeimatNation>
				<ZugangCode>9</ZugangCode>
				<ZugangDatum>18062009</ZugangDatum>
			<ZugangMaStgCode>1</ZugangMaStgCode>
			<ZugangMaStgDatum>21012013</ZugangMaStgDatum>
				<Ausstellungsstaat>A</Ausstellungsstaat>
			<BeginnDatum>11092014</BeginnDatum>
			<Ausbildungssemester>1</Ausbildungssemester>
			<StudStatusCode>1</StudStatusCode>
			<BerufstaetigkeitCode>7</BerufstaetigkeitCode>
					<StandortCode>14</StandortCode>
				<BMWFWfoerderrelevant>J</BMWFWfoerderrelevant>
		</StudentIn>
		<StudentIn>
			<PersKz>1410269017</PersKz>
			<OrgFormCode>2</OrgFormCode>
			<GeburtsDatum>22121987</GeburtsDatum>
			<Geschlecht>M</Geschlecht>
			<SVNR>1720221287</SVNR>
			<StaatsangehoerigkeitCode>A</StaatsangehoerigkeitCode>
			<HeimatPLZ>2201</HeimatPLZ>
			<HeimatGemeinde>Gerasdorf bei Wien</HeimatGemeinde>
			<HeimatStrasse><![CDATA[Stammersdorferstraße 258/2]]></HeimatStrasse>
			<HeimatNation>A</HeimatNation>
				<ZugangCode>4</ZugangCode>
				<ZugangDatum>16092011</ZugangDatum>
			<ZugangMaStgCode>1</ZugangMaStgCode>
			<ZugangMaStgDatum>03102014</ZugangMaStgDatum>
				<Ausstellungsstaat>A</Ausstellungsstaat>
			<BeginnDatum>11092014</BeginnDatum>
			<Ausbildungssemester>1</Ausbildungssemester>
			<StudStatusCode>1</StudStatusCode>
			<BerufstaetigkeitCode>10</BerufstaetigkeitCode>
					<StandortCode>14</StandortCode>
				<BMWFWfoerderrelevant>J</BMWFWfoerderrelevant>
		</StudentIn>
		<StudentIn>
			<PersKz>1410269018</PersKz>
			<OrgFormCode>2</OrgFormCode>
			<GeburtsDatum>21051986</GeburtsDatum>
			<Geschlecht>W</Geschlecht>
			<SVNR>4058210586</SVNR>
			<StaatsangehoerigkeitCode>A</StaatsangehoerigkeitCode>
			<HeimatPLZ>1140</HeimatPLZ>
			<HeimatGemeinde>Wien</HeimatGemeinde>
			<HeimatStrasse><![CDATA[Laurentiusplatz 1/7]]></HeimatStrasse>
			<HeimatNation>A</HeimatNation>
				<ZugangCode>14</ZugangCode>
				<ZugangDatum>01062005</ZugangDatum>
			<ZugangMaStgCode>1</ZugangMaStgCode>
			<ZugangMaStgDatum>31102013</ZugangMaStgDatum>
				<Ausstellungsstaat>A</Ausstellungsstaat>
			<BeginnDatum>11092014</BeginnDatum>
			<Ausbildungssemester>1</Ausbildungssemester>
			<StudStatusCode>1</StudStatusCode>
			<BerufstaetigkeitCode>6</BerufstaetigkeitCode>
					<StandortCode>14</StandortCode>
				<BMWFWfoerderrelevant>J</BMWFWfoerderrelevant>
		</StudentIn>
		<StudentIn>
			<PersKz>1410269019</PersKz>
			<OrgFormCode>2</OrgFormCode>
			<GeburtsDatum>13081993</GeburtsDatum>
			<Geschlecht>W</Geschlecht>
			<SVNR>3194130893</SVNR>
			<StaatsangehoerigkeitCode>A</StaatsangehoerigkeitCode>
			<HeimatPLZ>2700</HeimatPLZ>
			<HeimatGemeinde>Wiener Neustadt</HeimatGemeinde>
			<HeimatStrasse><![CDATA[Hubertusgasse 8/9]]></HeimatStrasse>
			<HeimatNation>A</HeimatNation>
				<ZugangCode>9</ZugangCode>
				<ZugangDatum>15062011</ZugangDatum>
			<ZugangMaStgCode>1</ZugangMaStgCode>
			<ZugangMaStgDatum>03072014</ZugangMaStgDatum>
				<Ausstellungsstaat>A</Ausstellungsstaat>
			<BeginnDatum>11092014</BeginnDatum>
			<Ausbildungssemester>1</Ausbildungssemester>
			<StudStatusCode>1</StudStatusCode>
			<BerufstaetigkeitCode>0</BerufstaetigkeitCode>
					<StandortCode>14</StandortCode>
				<BMWFWfoerderrelevant>J</BMWFWfoerderrelevant>
		</StudentIn>
		<StudentIn>
			<PersKz>1410269020</PersKz>
			<OrgFormCode>2</OrgFormCode>
			<GeburtsDatum>30081985</GeburtsDatum>
			<Geschlecht>W</Geschlecht>
			<SVNR>1401300885</SVNR>
			<StaatsangehoerigkeitCode>A</StaatsangehoerigkeitCode>
			<HeimatPLZ>3264</HeimatPLZ>
			<HeimatGemeinde>Gresten</HeimatGemeinde>
			<HeimatStrasse><![CDATA[Willi Sigmund Straße 5]]></HeimatStrasse>
			<HeimatNation>A</HeimatNation>
				<ZugangCode>10</ZugangCode>
				<ZugangDatum>03062003</ZugangDatum>
			<ZugangMaStgCode>1</ZugangMaStgCode>
			<ZugangMaStgDatum>26062014</ZugangMaStgDatum>
				<Ausstellungsstaat>A</Ausstellungsstaat>
			<BeginnDatum>11092014</BeginnDatum>
			<Ausbildungssemester>1</Ausbildungssemester>
			<StudStatusCode>1</StudStatusCode>
			<BerufstaetigkeitCode>7</BerufstaetigkeitCode>
					<StandortCode>14</StandortCode>
				<BMWFWfoerderrelevant>J</BMWFWfoerderrelevant>
		</StudentIn>
		<StudentIn>
			<PersKz>1410269021</PersKz>
			<OrgFormCode>2</OrgFormCode>
			<GeburtsDatum>05051985</GeburtsDatum>
			<Geschlecht>M</Geschlecht>
			<SVNR>1978050585</SVNR>
			<StaatsangehoerigkeitCode>A</StaatsangehoerigkeitCode>
			<HeimatPLZ>8020</HeimatPLZ>
			<HeimatGemeinde>Graz</HeimatGemeinde>
			<HeimatStrasse><![CDATA[Lagergasse 53b 14]]></HeimatStrasse>
			<HeimatNation>A</HeimatNation>
				<ZugangCode>10</ZugangCode>
				<ZugangDatum>15062005</ZugangDatum>
			<ZugangMaStgCode>1</ZugangMaStgCode>
			<ZugangMaStgDatum>28082012</ZugangMaStgDatum>
				<Ausstellungsstaat>A</Ausstellungsstaat>
			<BeginnDatum>11092014</BeginnDatum>
			<Ausbildungssemester>1</Ausbildungssemester>
			<StudStatusCode>1</StudStatusCode>
			<BerufstaetigkeitCode>6</BerufstaetigkeitCode>
					<StandortCode>14</StandortCode>
				<BMWFWfoerderrelevant>J</BMWFWfoerderrelevant>
		</StudentIn>
		<StudentIn>
			<PersKz>1410269022</PersKz>
			<OrgFormCode>2</OrgFormCode>
			<GeburtsDatum>01081978</GeburtsDatum>
			<Geschlecht>M</Geschlecht>
			<SVNR>4687010878</SVNR>
			<StaatsangehoerigkeitCode>BSH</StaatsangehoerigkeitCode>
			<HeimatPLZ>1150</HeimatPLZ>
			<HeimatGemeinde>Wien</HeimatGemeinde>
			<HeimatStrasse><![CDATA[Kröllgasse 1/15]]></HeimatStrasse>
			<HeimatNation>A</HeimatNation>
				<ZugangCode>5</ZugangCode>
				<ZugangDatum>13061997</ZugangDatum>
			<ZugangMaStgCode>1</ZugangMaStgCode>
			<ZugangMaStgDatum>28022013</ZugangMaStgDatum>
				<Ausstellungsstaat>A</Ausstellungsstaat>
			<BeginnDatum>11092014</BeginnDatum>
			<Ausbildungssemester>1</Ausbildungssemester>
			<StudStatusCode>1</StudStatusCode>
			<BerufstaetigkeitCode>9</BerufstaetigkeitCode>
					<StandortCode>14</StandortCode>
				<BMWFWfoerderrelevant>J</BMWFWfoerderrelevant>
		</StudentIn>
		<StudentIn>
			<PersKz>1410269023</PersKz>
			<OrgFormCode>2</OrgFormCode>
			<GeburtsDatum>21051989</GeburtsDatum>
			<Geschlecht>W</Geschlecht>
			<SVNR>2032210589</SVNR>
			<StaatsangehoerigkeitCode>A</StaatsangehoerigkeitCode>
			<HeimatPLZ>2700</HeimatPLZ>
			<HeimatGemeinde>Wiener Neustadt</HeimatGemeinde>
			<HeimatStrasse><![CDATA[Baumkirchnerring 5/Top2]]></HeimatStrasse>
			<HeimatNation>A</HeimatNation>
				<ZugangCode>13</ZugangCode>
				<ZugangDatum>03062008</ZugangDatum>
			<ZugangMaStgCode>1</ZugangMaStgCode>
			<ZugangMaStgDatum>08072011</ZugangMaStgDatum>
				<Ausstellungsstaat>A</Ausstellungsstaat>
			<BeginnDatum>11092014</BeginnDatum>
			<Ausbildungssemester>1</Ausbildungssemester>
			<StudStatusCode>1</StudStatusCode>
			<BerufstaetigkeitCode>6</BerufstaetigkeitCode>
					<StandortCode>14</StandortCode>
				<BMWFWfoerderrelevant>J</BMWFWfoerderrelevant>
		</StudentIn>
		<StudentIn>
			<PersKz>1410269024</PersKz>
			<OrgFormCode>2</OrgFormCode>
			<GeburtsDatum>28041989</GeburtsDatum>
			<Geschlecht>W</Geschlecht>
			<SVNR>3798280489</SVNR>
			<StaatsangehoerigkeitCode>A</StaatsangehoerigkeitCode>
			<HeimatPLZ>8010</HeimatPLZ>
			<HeimatGemeinde>Graz</HeimatGemeinde>
			<HeimatStrasse><![CDATA[Paracelsusgasse 2/11]]></HeimatStrasse>
			<HeimatNation>A</HeimatNation>
				<ZugangCode>9</ZugangCode>
				<ZugangDatum>15062007</ZugangDatum>
			<ZugangMaStgCode>1</ZugangMaStgCode>
			<ZugangMaStgDatum>22072010</ZugangMaStgDatum>
				<Ausstellungsstaat>A</Ausstellungsstaat>
			<BeginnDatum>11092014</BeginnDatum>
			<Ausbildungssemester>1</Ausbildungssemester>
			<StudStatusCode>1</StudStatusCode>
			<BerufstaetigkeitCode>7</BerufstaetigkeitCode>
					<StandortCode>14</StandortCode>
				<BMWFWfoerderrelevant>J</BMWFWfoerderrelevant>
		</StudentIn>
		<StudentIn>
			<PersKz>1410269025</PersKz>
			<OrgFormCode>2</OrgFormCode>
			<GeburtsDatum>28031986</GeburtsDatum>
			<Geschlecht>W</Geschlecht>
			<SVNR>5234280386</SVNR>
			<StaatsangehoerigkeitCode>BSH</StaatsangehoerigkeitCode>
			<HeimatPLZ>1150</HeimatPLZ>
			<HeimatGemeinde>Wien</HeimatGemeinde>
			<HeimatStrasse><![CDATA[Kröllgasse 1/15]]></HeimatStrasse>
			<HeimatNation>A</HeimatNation>
				<ZugangCode>5</ZugangCode>
				<ZugangDatum>28082010</ZugangDatum>
			<ZugangMaStgCode>1</ZugangMaStgCode>
			<ZugangMaStgDatum>22102013</ZugangMaStgDatum>
				<Ausstellungsstaat>A</Ausstellungsstaat>
			<BeginnDatum>11092014</BeginnDatum>
			<Ausbildungssemester>1</Ausbildungssemester>
			<StudStatusCode>1</StudStatusCode>
			<BerufstaetigkeitCode>6</BerufstaetigkeitCode>
					<StandortCode>14</StandortCode>
				<BMWFWfoerderrelevant>J</BMWFWfoerderrelevant>
		</StudentIn>
			<BewerberInnen>
			<OrgFormCode>2</OrgFormCode>
				<ZugangMaStgCode>1</ZugangMaStgCode>
				<AnzBewerberM>3</AnzBewerberM>
				<AnzBewerberW>17</AnzBewerberW>
			</BewerberInnen>
			<BewerberInnen>
			<OrgFormCode>2</OrgFormCode>
				<ZugangMaStgCode>7</ZugangMaStgCode>
				<AnzBewerberM>0</AnzBewerberM>
				<AnzBewerberW>1</AnzBewerberW>
			</BewerberInnen>
			<BewerberInnen>
			<OrgFormCode>2</OrgFormCode>
				<ZugangMaStgCode>9</ZugangMaStgCode>
				<AnzBewerberM>1</AnzBewerberM>
				<AnzBewerberW>1</AnzBewerberW>
			</BewerberInnen>
			<BewerberInnen>
			<OrgFormCode>2</OrgFormCode>
				<ZugangMaStgCode>3</ZugangMaStgCode>
				<AnzBewerberM>0</AnzBewerberM>
				<AnzBewerberW>1</AnzBewerberW>
			</BewerberInnen>
			<BewerberInnen>
			<OrgFormCode>2</OrgFormCode>
				<ZugangMaStgCode>2</ZugangMaStgCode>
				<AnzBewerberM>1</AnzBewerberM>
				<AnzBewerberW>0</AnzBewerberW>
			</BewerberInnen>
    </Studiengang>
  </StudierendenBewerberMeldung>
</Erhalter>